[
    {
        "id": 1,
        "buyer": "Abigail",
        "status": "已出貨",
        "seller": "Evans（埃文斯）",
        "name": "【CASIO 】12位元繽紛馬卡龍色系便利型計算機-MS-20UC系列~原廠保固24個月",
        "typeId": 31,
        "type": "文具、美術用具",
        "subType": "學校、辦公用品",
        "item": "計算器",
        "picture": "ID1.jpg",
        "description": "■ MS-20UC\n■ 12位數 \n■ 獨立記憶體\n■ 百分比計算\n■ 利潤率計算\n■ 開根號計算 \n■ 正負數顯示\n■ 倒退鍵\n■ 千分位符號\n■ 時間計算 \n■ 稅金計算\n■ 太陽能和電池雙電力\n■ 長149.5*寬105*高22.8mm\n■ 重量110g",
        "price": 399,
        "amount": 6,
        "fare": 30
    },
    {
        "id": 2,
        "buyer": "Ada",
        "status": "已收貨",
        "seller": "Davies（戴維斯）",
        "name": "【CASIO 】12位元繽紛馬卡龍色系便利型計算機-MS-20UC系列~原廠保固24個月",
        "typeId": 31,
        "type": "文具、美術用具",
        "subType": "學校、辦公用品",
        "item": "計算器",
        "picture": "ID1.jpg",
        "description": "■ MS-20UC\n■ 12位數 \n■ 獨立記憶體\n■ 百分比計算\n■ 利潤率計算\n■ 開根號計算 \n■ 正負數顯示\n■ 倒退鍵\n■ 千分位符號\n■ 時間計算 \n■ 稅金計算\n■ 太陽能和電池雙電力\n■ 長149.5*寬105*高22.8mm\n■ 重量110g",
        "price": 450,
        "amount": 8,
        "fare": 60
    },
    {
        "id": 3,
        "buyer": "Alice",
        "status": "完成訂單",
        "seller": "Lewis（劉易斯）",
        "name": "ASUS_華碩S500TE系列 - i3處理器 - 8G記憶體\n512G SSD / Win11家用版電腦",
        "typeId": 1,
        "type": "電腦與周邊配件",
        "subType": "桌上型電腦",
        "item": "桌上型電腦",
        "picture": "ID41.jpg,ID41_2.jpg",
        "description": "規格說明\n處理器：Intel Core i3-13100\n晶片：Intel B760\n記憶體：記憶體：8GB DDR4 3200MHz = (8G x 1條)(Long-DIMM(U-DIMM)記憶體支援容量 : 總插槽數量 2 / 最高容量64G)\n硬碟：512GB M.2 2280 NVMe™ PCIe® 4.0 SSD(擴充硬碟需自行購買螺絲)\n顯示介面：內顯\n光碟機：無\n讀卡機：無\n鍵鼠組：有\n音效：High Definition 7.1 Channel Audio\n螢幕輸出介面：D-Sub(VGA)．HDMI．DP\n無線網路：Wi-Fi 5(802.11ac) (Dual band) 1*1 + Bluetooth® 5.1 Wireless Card\n有線網路：Intel WGI219V 10/100/1000 Mbps, non-vPro\n電源供應：300W power supply (80+ Bronze, peak 350W)\n作業系統：Windows 11 家用版 (64 bit)\n保固：原廠三年保固/到府收送\n(免費第一年到府維修)\n(原廠於保固期內將自行或委託第三方到府收送) \n\n●前端 I/O Port\t\n1x Headphone\n1x Mic in\n2x USB 2.0 Type-A\n2x USB 3.2 Gen 1 Type-A\n\n●後端 I/O Port\t\n1x RJ45 Gigabit Ethernet\n1x HDMI 1.4\n1x VGA Port\n1x Display port 1.4\n2x PS2\n3x Audio jacks\n2x USB 2.0 Type-A\n2x USB 3.2 Gen 1 Type-A\n\n●擴充槽(含已使用)\n2x 3.5\"\n4x SATA 6.0Gb/s ports\n2x M.2 connector for storage\n1x PCIe® 4.0 x 16\n2x PCIe® 3.0 x 1\n1x M.2 connector for WiFi\n2x DDR4 U-DIMM slot\n\n體積：17.60 x 39.30 x 38.50 cm (6.93\" x 15.47\" x 15.16\")\n重量：7.70 kg (16.98 lbs)",
        "price": 14000,
        "amount": 15,
        "fare": 1000
    },
    {
        "id": 4,
        "buyer": "Anna",
        "status": "已收貨",
        "seller": "Lewis（劉易斯）",
        "name": "ASUS_華碩S500TE系列 - i3處理器 - 8G記憶體\n512G SSD / 無作業系統電腦",
        "typeId": 1,
        "type": "電腦與周邊配件",
        "subType": "桌上型電腦",
        "item": "桌上型電腦",
        "picture": "ID72.jpg,ID72_2.jpg",
        "description": "處理器：Intel Core i3-13100\n晶片：Intel B760\n記憶體：記憶體：8GB DDR4 3200MHz = (8G x 1條)(Long-DIMM(U-DIMM)記憶體支援容量 : 總插槽數量 2 / 最高容量64G)\n硬碟：512GB M.2 2280 NVMe™ PCIe® 4.0 SSD(擴充硬碟需自行購買螺絲)\n顯示介面：內顯\n光碟機：無\n讀卡機：無\n鍵鼠組：有\n音效：High Definition 7.1 Channel Audio\n螢幕輸出介面：D-Sub(VGA)．HDMI．DP\n無線網路：Wi-Fi 5(802.11ac) (Dual band) 1*1 + Bluetooth® 5.1 Wireless Card\n有線網路：Intel WGI219V 10/100/1000 Mbps, non-vPro\n電源供應：300W power supply (80+ Bronze, peak 350W)\n作業系統：無作業系統\n保固：原廠三年保固/到府收送\n(免費第一年到府維修)\n(原廠於保固期內將自行或委託第三方到府收送) \n\n●前端 I/O Port\t\n1x Headphone\n1x Mic in\n2x USB 2.0 Type-A\n2x USB 3.2 Gen 1 Type-A\n\n●後端 I/O Port\t\n1x RJ45 Gigabit Ethernet\n1x HDMI 1.4\n1x VGA Port\n1x Display port 1.4\n2x PS2\n3x Audio jacks\n2x USB 2.0 Type-A\n2x USB 3.2 Gen 1 Type-A\n\n●擴充槽(含已使用)\n2x 3.5\"\n4x SATA 6.0Gb/s ports\n2x M.2 connector for storage\n1x PCIe® 4.0 x 16\n2x PCIe® 3.0 x 1\n1x M.2 connector for WiFi\n2x DDR4 U-DIMM slot\n\n體積：17.60 x 39.30 x 38.50 cm (6.93\" x 15.47\" x 15.16\")\n重量：7.70 kg (16.98 lbs)",
        "price": 12000,
        "amount": 8,
        "fare": 1
    },
    {
        "id": 5,
        "buyer": "Abbie",
        "status": "完成訂單",
        "seller": "Patel（帕特爾）",
        "name": "MSI_微星13代i3四核心 獨顯\nMSI PRO DP180 i3-13100F/16G/1TB+512G SSD/P600_2G/500W/W11P",
        "typeId": 1,
        "type": "電腦與周邊配件",
        "subType": "桌上型電腦",
        "item": "桌上型電腦",
        "picture": "ID10.jpg",
        "description": "●主機主要規格\n．品牌：MSI 微星\n．主機型號：PRO DP180\n．晶片組：H610\n．處理器：Intel Core i3-13100F (4-Core, 12M Cache, 3.4GHz to 4.5GHz)\n．記憶體：16G DDR4\n．系統記憶體插槽數：2 個\n．記憶體最高支援容量：64GB\n．固態硬碟：512G M.2 PCIe SSD\n．傳統硬碟：1TB HDD\n．顯示功能類型：獨立顯示卡\n．顯示卡型號：已加裝NVIDIA Quadro P600 2G GDDR5 (三年保固 特仕升級) \n．顯示卡記憶體類型：GDDR5 \n．顯示卡記憶體容量：2G \n．光碟機：無\n．作業系統：Windows 11 Pro\n．主機型態：一般桌上型\n●其他規格\n．音效裝置：Realtek ALC897, 7.1 Channel HD Audio\n．區域網路：2.5G+1G LAN (Intel I226-V+Intel I219-V)\n．無線網路：Wi-Fi 6E\n．藍牙：Bluetooth 5.3\n．電源供應器：500W, 80PLUS BRONZE, ATX, POWER SUPPLY\n．鍵鼠組：無\n●前端面板\n．1x Headphone-out\n．1x Mic-in\n．2x Type A USB 3.2 Gen 1 \n．1x Type C USB 3.2 Gen 2 \n．1x Card Reader (SD & Micros SD card support)\n●後端面板\n．2x Type A USB 2.0\n．1x PS/2\n．1x Type A USB 3.2 Gen 1\n．1x 2.5G LAN\n．2x Type A USB 2.0 \n．1x RJ45 LAN (1G)\n．3x Audio Jacks\n．1x Padlock 機箱掛鎖\n．1x COM Port \n．1x Kensington Lock 防盜鎖孔\n●視訊面板\n．4 x Mini DisplayPort \n●機殼規格\n．尺寸：168 x 323 x 369mm\n．重量：5Kg以上\n●注意事項\n．保固說明：三年保固 (到府收送)\n．本商品不含螢幕傳輸線、螢幕轉接頭，請另外購買\n．此機原廠保固：不包含加裝記憶體、硬碟、顯示卡《由代理商保固》",
        "price": 29900,
        "amount": 7,
        "fare": 1
    },
    {
        "id": 6,
        "buyer": "Aria",
        "status": "完成訂單",
        "seller": "Harris（哈里斯）",
        "name": "KINYO 藍芽4.2多功能無線接收器 適用 iPhone Xr, Xs, Xs Max, HTC U12 等無 3.5mm孔手機, 及車用喇叭 音響 有線耳機 藍芽接受器",
        "typeId": 28,
        "type": "影音",
        "subType": "音響/喇叭",
        "item": "音響喇叭",
        "picture": "ID11.jpg",
        "description": "◆4.2藍牙技術，天線效率有效最佳化，強化通訊能力。\n◆原音重現，高保真技術，不因無線化而影響最佳音質。\n◆大容量電池，可邊充電邊用，超長使用時間，不須擔心沒電斷訊。\n◆內建TF卡槽，可讀取Micro SD記憶卡內建音樂\n◆具來電接聽/掛斷，音量調整，播放/暫停，上/下曲切換功能。\n◆內建夾扣，不論何時，皆可夾上衣服使用。",
        "price": 499,
        "amount": 14,
        "fare": 30
    },
    {
        "id": 7,
        "buyer": "Anna",
        "status": "完成訂單",
        "seller": "Davies（戴維斯）",
        "name": "CASIO 12位數金屬面板計算機-黑灰色MX-120B",
        "typeId": 31,
        "type": "文具、美術用具",
        "subType": "學校、辦公用品",
        "item": "計算器",
        "picture": "ID12.jpg",
        "description": "ID12D.jpg",
        "price": 360,
        "amount": 8,
        "fare": 60
    },
    {
        "id": 8,
        "buyer": "Ava",
        "status": "已出貨",
        "seller": "Green（格林）",
        "name": "KINYO 藍芽4.2多功能無線接收器 適用 iPhone Xr, Xs, Xs Max, HTC U12 等無 3.5mm孔手機, 及車用喇叭 音響 有線耳機 藍芽接受器",
        "typeId": 28,
        "type": "影音",
        "subType": "音響/喇叭",
        "item": "音響喇叭",
        "picture": "ID11.jpg",
        "description": "◆4.2藍牙技術，天線效率有效最佳化，強化通訊能力。\n◆原音重現，高保真技術，不因無線化而影響最佳音質。\n◆大容量電池，可邊充電邊用，超長使用時間，不須擔心沒電斷訊。\n◆內建TF卡槽，可讀取Micro SD記憶卡內建音樂\n◆具來電接聽/掛斷，音量調整，播放/暫停，上/下曲切換功能。\n◆內建夾扣，不論何時，皆可夾上衣服使用。",
        "price": 550,
        "amount": 5,
        "fare": 60
    },
    {
        "id": 9,
        "buyer": "Amelia",
        "status": "已出貨",
        "seller": "Edwards（愛德華茲）",
        "name": "CASIO 12位數金屬面板計算機-黑灰色MX-120B",
        "typeId": 31,
        "type": "文具、美術用具",
        "subType": "學校、辦公用品",
        "item": "計算器",
        "picture": "ID12.jpg",
        "description": "ID12D.jpg",
        "price": 300,
        "amount": 16,
        "fare": 30
    },
    {
        "id": 10,
        "buyer": "Ann",
        "status": "已收貨",
        "seller": "Lewis（劉易斯）",
        "name": "ASUS_華碩S501MD系列 - i5處理器 - 16G記憶體\n1TB SSD / INTEL Arc A380顯卡 / Win11家用版電腦",
        "typeId": 1,
        "type": "電腦與周邊配件",
        "subType": "桌上型電腦",
        "item": "桌上型電腦",
        "picture": "ID81.jpg,ID81_2.jpg",
        "description": "處理器：Intel Core i5-12400F\n主機板晶片組：Intel B660\n記憶體：16GB DDR4 3200MHz = (16G x 1條)(Long-DIMM(U-DIMM) 記憶體支援容量 : 總插槽數量 2 / 最高容量64G)\n硬碟：1TB M.2 2280 NVMe™ PCIe® 3.0 SSD(擴充SATA HDD需購買螺絲*)\n顯示介面：INTEL® Arc™ A380 6GB GDDR6 : 3x DP, 1x HDMI\n光碟機：無\n讀卡機：無\n鍵鼠組：無\n音效：High Definition 7.1 Channel Audio\n螢幕輸出介面：HDMI．DP\n無線網路：Wi-Fi 5(802.11ac) (Dual band) 1*1 + Bluetooth® 5.1 Wireless Card\n有線網路：Intel WGI219V 10/100/1000 Mbps, non-vPro\n電源供應：300W power supply (80+ Bronze, peak 350W)\n作業系統：Windows 11 家用版 (64 bit)\n保固：原廠三年保固/到府收送\n(免費第一年到府維修)\n(原廠於保固期內將自行或委託第三方到府收送)\n\n●前端介面\n1x Headphone\n1x MIC in\n2x USB 2.0 Type-A\n2x USB 3.2 Gen 1 Type-A\n\n●後端介面\n1x RJ45 Gigabit Ethernet\n2x PS2\n3 x Audio jacks\n2x USB 2.0 Type-A\n2x USB 3.2 Gen 1 Type-A\n3x DP (位於顯卡)\n1x HDMI (位於顯卡)\n\n●擴充介面(含已使用)\n1x 3.5\"\n4x SATA 6.0Gb/s ports\n2x M.2 connector for storage\n1x PCIe® 4.0 x 16\n2x PCIe® 3.0 x 1\n1x M.2 connector for WiFi\n2x DDR4 U-DIMM slot\n\n體積:16.00 x 31.89 x 36.78 cm\n重量:5.90 kg",
        "price": 17990,
        "amount": 16,
        "fare": 1500
    },
    {
        "id": 11,
        "buyer": "Ariana",
        "status": "已收貨",
        "seller": "Green（格林）",
        "name": "KINYO 藍牙5.0無線音箱 立體環繞360讀卡喇叭音響，支援藍芽/USB/TF卡/AUX，適用具藍牙功能或3.5mm插孔的平板電腦/筆記型電腦/智慧型手機",
        "typeId": 28,
        "type": "影音",
        "subType": "音響/喇叭",
        "item": "音響喇叭",
        "picture": "ID21.jpg",
        "description": "‧功能控制 藍牙/USB/TF卡/AUX\n‧介面 Bluetooth V5.0\n‧最大接收距離 10M(無任何障礙環境)\n‧輸出功率3W*2 (R.M.S.)\n‧額定電壓 USB DC 5V / 充電電池3.7V\n‧電池規格 聚合物鋰電池1200mAh\n‧消耗電流 200mA\n‧抗阻 4Ω\n‧噪音比 ≧80dB\n‧喇叭單體 2x40mm全音域喇叭\n‧響應頻率 120HZ-20KHz\n‧支援音樂格式MP3\n‧材質 塑料、金屬\n‧產品重量:618g\n‧產品尺寸:400x65x58(WxHxD)mm   \n‧配件 充電線x1、音源線x1",
        "price": 899,
        "amount": 6,
        "fare": 60
    },
    {
        "id": 12,
        "buyer": "Ann",
        "status": "已出貨",
        "seller": "Lewis（劉易斯）",
        "name": "ASUS_華碩S500TE系列 - i3處理器 - 8G記憶體\n512G SSD / Win11家用版電腦",
        "typeId": 1,
        "type": "電腦與周邊配件",
        "subType": "桌上型電腦",
        "item": "桌上型電腦",
        "picture": "ID85.jpg,ID85_2.jpg",
        "description": "處理器：Intel Core i3-13100\n晶片：Intel B760\n記憶體：記憶體：8GB DDR4 3200MHz = (8G x 1條)(Long-DIMM(U-DIMM)記憶體支援容量 : 總插槽數量 2 / 最高容量64G)\n硬碟：512GB M.2 2280 NVMe™ PCIe® 4.0 SSD(擴充硬碟需自行購買螺絲)\n顯示介面：內顯\n光碟機：無\n讀卡機：無\n鍵鼠組：有\n音效：High Definition 7.1 Channel Audio\n螢幕輸出介面：D-Sub(VGA)．HDMI．DP\n無線網路：Wi-Fi 5(802.11ac) (Dual band) 1*1 + Bluetooth® 5.1 Wireless Card\n有線網路：Intel WGI219V 10/100/1000 Mbps, non-vPro\n電源供應：300W power supply (80+ Bronze, peak 350W)\n作業系統：Windows 11 家用版 (64 bit)\n保固：原廠三年保固/到府收送\n(免費第一年到府維修)\n(原廠於保固期內將自行或委託第三方到府收送) \n\n●前端 I/O Port\t\n1x Headphone\n1x Mic in\n2x USB 2.0 Type-A\n2x USB 3.2 Gen 1 Type-A\n\n●後端 I/O Port\t\n1x RJ45 Gigabit Ethernet\n1x HDMI 1.4\n1x VGA Port\n1x Display port 1.4\n2x PS2\n3x Audio jacks\n2x USB 2.0 Type-A\n2x USB 3.2 Gen 1 Type-A\n\n●擴充槽(含已使用)\n2x 3.5\"\n4x SATA 6.0Gb/s ports\n2x M.2 connector for storage\n1x PCIe® 4.0 x 16\n2x PCIe® 3.0 x 1\n1x M.2 connector for WiFi\n2x DDR4 U-DIMM slot\n\n體積：17.60 x 39.30 x 38.50 cm (6.93\" x 15.47\" x 15.16\")\n重量：7.70 kg (16.98 lbs)",
        "price": 14618,
        "amount": 6,
        "fare": 1000
    },
    {
        "id": 13,
        "buyer": "Amelia",
        "status": "待出貨",
        "seller": "Brown（布朗）",
        "name": "WD_威騰WD_BLACK D10 Game Drive 8TB 3.5吋電競外接式硬碟(WDBA3P0080HBK-SESN)",
        "typeId": 11,
        "type": "電腦與周邊配件",
        "subType": "儲存裝置",
        "item": "內接硬碟/外接硬碟",
        "picture": "ID26.jpg",
        "description": "ID26D.jpg",
        "price": 7590,
        "amount": 15,
        "fare": 100
    },
    {
        "id": 14,
        "buyer": "Ada",
        "status": "已出貨",
        "seller": "Clarke（克拉克）",
        "name": "WD_威騰WD_BLACK D10 Game Drive 8TB 3.5吋電競外接式硬碟(WDBA3P0080HBK-SESN)",
        "typeId": 11,
        "type": "電腦與周邊配件",
        "subType": "儲存裝置",
        "item": "內接硬碟/外接硬碟",
        "picture": "ID26.jpg",
        "description": "ID26D.jpg",
        "price": 8000,
        "amount": 15,
        "fare": 100
    },
    {
        "id": 15,
        "buyer": "Aurora",
        "status": "已出貨",
        "seller": "Jackson（傑克遜）",
        "name": "KINYO 藍芽4.2多功能無線接收器 適用 iPhone Xr, Xs, Xs Max, HTC U12 等無 3.5mm孔手機, 及車用喇叭 音響 有線耳機 藍芽接受器",
        "typeId": 28,
        "type": "影音",
        "subType": "音響/喇叭",
        "item": "音響喇叭",
        "picture": "ID11.jpg",
        "description": "◆4.2藍牙技術，天線效率有效最佳化，強化通訊能力。\n◆原音重現，高保真技術，不因無線化而影響最佳音質。\n◆大容量電池，可邊充電邊用，超長使用時間，不須擔心沒電斷訊。\n◆內建TF卡槽，可讀取Micro SD記憶卡內建音樂\n◆具來電接聽/掛斷，音量調整，播放/暫停，上/下曲切換功能。\n◆內建夾扣，不論何時，皆可夾上衣服使用。",
        "price": 600,
        "amount": 17,
        "fare": 30
    },
    {
        "id": 16,
        "buyer": "Aria",
        "status": "已出貨",
        "seller": "Brown（布朗）",
        "name": "WD My Passport 4TB 2.5吋行動硬碟-藍(WDBPKJ0040BBL-WESN)",
        "typeId": 11,
        "type": "電腦與周邊配件",
        "subType": "儲存裝置",
        "item": "內接硬碟/外接硬碟",
        "picture": "ID32.jpg",
        "description": "ID32D.jpg",
        "price": 3190,
        "amount": 20,
        "fare": 60
    },
    {
        "id": 17,
        "buyer": "Ann",
        "status": "待出貨",
        "seller": "Evans（埃文斯）",
        "name": "CASIO 12位數金屬面板計算機-黑灰色MX-120B",
        "typeId": 31,
        "type": "文具、美術用具",
        "subType": "學校、辦公用品",
        "item": "計算器",
        "picture": "ID12.jpg",
        "description": "ID12D.jpg",
        "price": 400,
        "amount": 5,
        "fare": 1
    },
    {
        "id": 18,
        "buyer": "Ada",
        "status": "已收貨",
        "seller": "Davies（戴維斯）",
        "name": "【CASIO 】10位元繽紛馬卡龍色迷你型計算機-薄荷綠 (MS-7UC-GN)",
        "typeId": 31,
        "type": "文具、美術用具",
        "subType": "學校、辦公用品",
        "item": "計算器",
        "picture": "ID34.jpg",
        "description": "型號：MS-7UC-GN\n類型：迷你桌上型\n顯示：負數（-），常數（K），錯誤（E），功能命令符號，3位逗號標記，記憶（M），稅務計算符號（TAX+/TAX-），時間計算符號\n計算功能：基本四則計算操作，稅務計算，常數計算，利潤率百分比計算，近似計算，開方根計算，時間計算\n數字：10位數字\n記憶體：獨立記憶體，稅率計算記憶體\n電源：雙向電源-太陽能和鋰電池 (1 × LR1130)\n鋰電池壽命：LR1130約3年（每天使用1小時）\n自動關機系統：大約每6分鐘自動關機\n尺寸(H × W × D mm)：19.4 × 85 × 120\n重量：約70 克 (含鋰電池)",
        "price": 319,
        "amount": 14,
        "fare": 60
    },
    {
        "id": 19,
        "buyer": "Ada",
        "status": "已出貨",
        "seller": "Clarke（克拉克）",
        "name": "WD My Passport 4TB 2.5吋行動硬碟-藍(WDBPKJ0040BBL-WESN)",
        "typeId": 11,
        "type": "電腦與周邊配件",
        "subType": "儲存裝置",
        "item": "內接硬碟/外接硬碟",
        "picture": "ID32.jpg",
        "description": "ID32D.jpg",
        "price": 3000,
        "amount": 11,
        "fare": 60
    },
    {
        "id": 20,
        "buyer": "Aria",
        "status": "完成訂單",
        "seller": "Hughes（休斯）",
        "name": "KINYO 藍芽4.2多功能無線接收器 適用 iPhone Xr, Xs, Xs Max, HTC U12 等無 3.5mm孔手機, 及車用喇叭 音響 有線耳機 藍芽接受器",
        "typeId": 28,
        "type": "影音",
        "subType": "音響/喇叭",
        "item": "音響喇叭",
        "picture": "ID11.jpg",
        "description": "◆4.2藍牙技術，天線效率有效最佳化，強化通訊能力。\n◆原音重現，高保真技術，不因無線化而影響最佳音質。\n◆大容量電池，可邊充電邊用，超長使用時間，不須擔心沒電斷訊。\n◆內建TF卡槽，可讀取Micro SD記憶卡內建音樂\n◆具來電接聽/掛斷，音量調整，播放/暫停，上/下曲切換功能。\n◆內建夾扣，不論何時，皆可夾上衣服使用。",
        "price": 500,
        "amount": 19,
        "fare": 1
    },
    {
        "id": 21,
        "buyer": "Alice",
        "status": "已收貨",
        "seller": "Davies（戴維斯）",
        "name": "【CASIO】12位數工程型計算機2代-(FX-991ESPLUS-2)",
        "typeId": 31,
        "type": "文具、美術用具",
        "subType": "學校、辦公用品",
        "item": "計算器",
        "picture": "ID39.jpg",
        "description": "數學自然顯示\n417個函數\n自然V.P.A.M. 顯示\n如同教科書般的顯示方式\n條列式統計資料編輯器\n多重重現顯示\n10 + 2位數\n新等式模式\n隨機整數\n分數計算\n組合與排列\n統計\n9個變數\n表格函數\n點矩陣顯示\n雙電源系統\n附帶硬式外殼\n尺寸：11.1x77x161.5mm\n重量：95g",
        "price": 799,
        "amount": 12,
        "fare": 1
    },
    {
        "id": 22,
        "buyer": "Amelia",
        "status": "已出貨",
        "seller": "Patel（帕特爾）",
        "name": "ASUS_華碩S500TE系列 - i3處理器 - 8G記憶體\n512G SSD / Win11家用版電腦",
        "typeId": 1,
        "type": "電腦與周邊配件",
        "subType": "桌上型電腦",
        "item": "桌上型電腦",
        "picture": "ID41.jpg,ID41_2.jpg",
        "description": "規格說明\n處理器：Intel Core i3-13100\n晶片：Intel B760\n記憶體：記憶體：8GB DDR4 3200MHz = (8G x 1條)(Long-DIMM(U-DIMM)記憶體支援容量 : 總插槽數量 2 / 最高容量64G)\n硬碟：512GB M.2 2280 NVMe™ PCIe® 4.0 SSD(擴充硬碟需自行購買螺絲)\n顯示介面：內顯\n光碟機：無\n讀卡機：無\n鍵鼠組：有\n音效：High Definition 7.1 Channel Audio\n螢幕輸出介面：D-Sub(VGA)．HDMI．DP\n無線網路：Wi-Fi 5(802.11ac) (Dual band) 1*1 + Bluetooth® 5.1 Wireless Card\n有線網路：Intel WGI219V 10/100/1000 Mbps, non-vPro\n電源供應：300W power supply (80+ Bronze, peak 350W)\n作業系統：Windows 11 家用版 (64 bit)\n保固：原廠三年保固/到府收送\n(免費第一年到府維修)\n(原廠於保固期內將自行或委託第三方到府收送) \n\n●前端 I/O Port\t\n1x Headphone\n1x Mic in\n2x USB 2.0 Type-A\n2x USB 3.2 Gen 1 Type-A\n\n●後端 I/O Port\t\n1x RJ45 Gigabit Ethernet\n1x HDMI 1.4\n1x VGA Port\n1x Display port 1.4\n2x PS2\n3x Audio jacks\n2x USB 2.0 Type-A\n2x USB 3.2 Gen 1 Type-A\n\n●擴充槽(含已使用)\n2x 3.5\"\n4x SATA 6.0Gb/s ports\n2x M.2 connector for storage\n1x PCIe® 4.0 x 16\n2x PCIe® 3.0 x 1\n1x M.2 connector for WiFi\n2x DDR4 U-DIMM slot\n\n體積：17.60 x 39.30 x 38.50 cm (6.93\" x 15.47\" x 15.16\")\n重量：7.70 kg (16.98 lbs)",
        "price": 14618,
        "amount": 15,
        "fare": 500
    },
    {
        "id": 23,
        "buyer": "Abbie",
        "status": "待出貨",
        "seller": "Harris（哈里斯）",
        "name": "KINYO 藍牙5.0無線音箱 立體環繞360讀卡喇叭音響，支援藍芽/USB/TF卡/AUX，適用具藍牙功能或3.5mm插孔的平板電腦/筆記型電腦/智慧型手機",
        "typeId": 28,
        "type": "影音",
        "subType": "音響/喇叭",
        "item": "音響喇叭",
        "picture": "ID21.jpg",
        "description": "‧功能控制 藍牙/USB/TF卡/AUX\n‧介面 Bluetooth V5.0\n‧最大接收距離 10M(無任何障礙環境)\n‧輸出功率3W*2 (R.M.S.)\n‧額定電壓 USB DC 5V / 充電電池3.7V\n‧電池規格 聚合物鋰電池1200mAh\n‧消耗電流 200mA\n‧抗阻 4Ω\n‧噪音比 ≧80dB\n‧喇叭單體 2x40mm全音域喇叭\n‧響應頻率 120HZ-20KHz\n‧支援音樂格式MP3\n‧材質 塑料、金屬\n‧產品重量:618g\n‧產品尺寸:400x65x58(WxHxD)mm   \n‧配件 充電線x1、音源線x1",
        "price": 950,
        "amount": 20,
        "fare": 60
    },
    {
        "id": 24,
        "buyer": "Alice",
        "status": "已出貨",
        "seller": "Lewis（劉易斯）",
        "name": "ASUS_華碩S500SE系列 - i5處理器 - 8G記憶體\n512G SSD / Win11家用版電腦",
        "typeId": 1,
        "type": "電腦與周邊配件",
        "subType": "桌上型電腦",
        "item": "桌上型電腦",
        "picture": "ID121.jpg,ID121_2.jpg",
        "description": "處理器：Intel Core i5-13400\n主機板晶片組：Intel B760\n記憶體：8GB DDR4 3200MHz = (8G x 1條)(Long-DIMM(U-DIMM) 記憶體支援容量 : 總插槽數量 2 / 最高容量64G)\n硬碟：512GB M.2 NVMe™ PCIe4.0 SSD(擴充硬碟需自行購買螺絲)\n顯示介面：內建\n光碟機：DVD writer 8X\n讀卡機：有\n鍵鼠組：有\n音效：High Definition 7.1 Channel Audio\n螢幕輸出介面：HDMI．D-Sub(VGA)\n無線網路：Wi-Fi 5(802.11ac) (Dual band) 1*1 + Bluetooth® 5.1 Wireless Card\n有線網路：Intel WGI219V 10/100/1000 GbE, non-vPro\n電源供應：300W power supply (80+ Platinum, peak 390W)\n作業系統：Windows 11 家用版 (64 bit)\n保固：原廠三年保固/到府收送\n(免費第一年到府維修)\n(原廠於保固期內將自行或委託第三方到府收送) \n\n●前端介面\n1x Headphone\n1x 3.5mm combo audio jack\n2x USB 3.2 Gen 1 Type-A\n2x USB 3.2 Gen 2 Type-A\n1x 2 in 1 card reader SD / MMC\n1x Smart card reader\n\n●後端介面\n1x Headphone out\n1x Line-in\n1x MIC in\n1x RJ45 Gigabit Ethernet\n1x HDMI 1.4\n1x VGA Port\n2x PS2\n4x USB 2.0 Type-A\n\n●擴充介面(含已使用)\n1x 2.5\" 擴充槽 (可安裝儲存設備)\n1x 3.5\" 擴充槽 (可安裝儲存設備)\n4x SATA 6.0Gb/s ports\n1x PCIe® 4.0 x 16\n2x PCIe® 3.0 x 1\n1x M.2 connector for WiFi\n2x M.2 connector for storage\n2x DDR4 U-DIMM slot\n\n體積:09.46 x 29.27 x 33.96 cm (3.72\" x 11.52\" x 13.37\")\n重量:05.00 kg (11.02 lbs)",
        "price": 19990,
        "amount": 15,
        "fare": 1500
    },
    {
        "id": 25,
        "buyer": "Anna",
        "status": "已收貨",
        "seller": "Hall（霍爾）",
        "name": "KINYO 藍芽4.2多功能無線接收器 適用 iPhone Xr, Xs, Xs Max, HTC U12 等無 3.5mm孔手機, 及車用喇叭 音響 有線耳機 藍芽接受器",
        "typeId": 28,
        "type": "影音",
        "subType": "音響/喇叭",
        "item": "音響喇叭",
        "picture": "ID11.jpg",
        "description": "◆4.2藍牙技術，天線效率有效最佳化，強化通訊能力。\n◆原音重現，高保真技術，不因無線化而影響最佳音質。\n◆大容量電池，可邊充電邊用，超長使用時間，不須擔心沒電斷訊。\n◆內建TF卡槽，可讀取Micro SD記憶卡內建音樂\n◆具來電接聽/掛斷，音量調整，播放/暫停，上/下曲切換功能。\n◆內建夾扣，不論何時，皆可夾上衣服使用。",
        "price": 580,
        "amount": 20,
        "fare": 30
    },
    {
        "id": 26,
        "buyer": "Aurora",
        "status": "完成訂單",
        "seller": "Lewis（劉易斯）",
        "name": "ASUS_華碩S500TE系列 - i3處理器 - 8G記憶體\n512G SSD / 無作業系統電腦",
        "typeId": 1,
        "type": "電腦與周邊配件",
        "subType": "桌上型電腦",
        "item": "桌上型電腦",
        "picture": "ID163.jpg,ID163_2.jpg",
        "description": "處理器：Intel Core i3-13100\n晶片：Intel B760\n記憶體：記憶體：8GB DDR4 3200MHz = (8G x 1條)(Long-DIMM(U-DIMM)記憶體支援容量 : 總插槽數量 2 / 最高容量64G)\n硬碟：512GB M.2 2280 NVMe™ PCIe® 4.0 SSD(擴充硬碟需自行購買螺絲)\n顯示介面：內顯\n光碟機：無\n讀卡機：無\n鍵鼠組：有\n音效：High Definition 7.1 Channel Audio\n螢幕輸出介面：D-Sub(VGA)．HDMI．DP\n無線網路：Wi-Fi 5(802.11ac) (Dual band) 1*1 + Bluetooth® 5.1 Wireless Card\n有線網路：Intel WGI219V 10/100/1000 Mbps, non-vPro\n電源供應：300W power supply (80+ Bronze, peak 350W)\n作業系統：無作業系統\n保固：原廠三年保固/到府收送\n(免費第一年到府維修)\n(原廠於保固期內將自行或委託第三方到府收送) \n\n●前端 I/O Port\t\n1x Headphone\n1x Mic in\n2x USB 2.0 Type-A\n2x USB 3.2 Gen 1 Type-A\n\n●後端 I/O Port\t\n1x RJ45 Gigabit Ethernet\n1x HDMI 1.4\n1x VGA Port\n1x Display port 1.4\n2x PS2\n3x Audio jacks\n2x USB 2.0 Type-A\n2x USB 3.2 Gen 1 Type-A\n\n●擴充槽(含已使用)\n2x 3.5\"\n4x SATA 6.0Gb/s ports\n2x M.2 connector for storage\n1x PCIe® 4.0 x 16\n2x PCIe® 3.0 x 1\n1x M.2 connector for WiFi\n2x DDR4 U-DIMM slot\n\n體積：17.60 x 39.30 x 38.50 cm (6.93\" x 15.47\" x 15.16\")\n重量：7.70 kg (16.98 lbs)",
        "price": 12618,
        "amount": 19,
        "fare": 1
    },
    {
        "id": 27,
        "buyer": "Aurora",
        "status": "已出貨",
        "seller": "Hall（霍爾）",
        "name": "KINYO 藍牙5.0無線音箱 立體環繞360讀卡喇叭音響，支援藍芽/USB/TF卡/AUX，適用具藍牙功能或3.5mm插孔的平板電腦/筆記型電腦/智慧型手機",
        "typeId": 28,
        "type": "影音",
        "subType": "音響/喇叭",
        "item": "音響喇叭",
        "picture": "ID21.jpg",
        "description": "‧功能控制 藍牙/USB/TF卡/AUX\n‧介面 Bluetooth V5.0\n‧最大接收距離 10M(無任何障礙環境)\n‧輸出功率3W*2 (R.M.S.)\n‧額定電壓 USB DC 5V / 充電電池3.7V\n‧電池規格 聚合物鋰電池1200mAh\n‧消耗電流 200mA\n‧抗阻 4Ω\n‧噪音比 ≧80dB\n‧喇叭單體 2x40mm全音域喇叭\n‧響應頻率 120HZ-20KHz\n‧支援音樂格式MP3\n‧材質 塑料、金屬\n‧產品重量:618g\n‧產品尺寸:400x65x58(WxHxD)mm   \n‧配件 充電線x1、音源線x1",
        "price": 1000,
        "amount": 5,
        "fare": 30
    },
    {
        "id": 28,
        "buyer": "Ada",
        "status": "待出貨",
        "seller": "Brown（布朗）",
        "name": "TCELL 冠元 TC200 USB3.2/Type C Gen2x2 1TB 超速外接式固態硬碟SSD (深海藍)",
        "typeId": 11,
        "type": "電腦與周邊配件",
        "subType": "儲存裝置",
        "item": "內接硬碟/外接硬碟",
        "picture": "ID51.jpg",
        "description": "ID51D.jpg",
        "price": 2999,
        "amount": 19,
        "fare": 1
    },
    {
        "id": 29,
        "buyer": "Abigail",
        "status": "已收貨",
        "seller": "Evans（埃文斯）",
        "name": "【CASIO 】10位元繽紛馬卡龍色迷你型計算機-薄荷綠 (MS-7UC-GN)",
        "typeId": 31,
        "type": "文具、美術用具",
        "subType": "學校、辦公用品",
        "item": "計算器",
        "picture": "ID34.jpg",
        "description": "型號：MS-7UC-GN\n類型：迷你桌上型\n顯示：負數（-），常數（K），錯誤（E），功能命令符號，3位逗號標記，記憶（M），稅務計算符號（TAX+/TAX-），時間計算符號\n計算功能：基本四則計算操作，稅務計算，常數計算，利潤率百分比計算，近似計算，開方根計算，時間計算\n數字：10位數字\n記憶體：獨立記憶體，稅率計算記憶體\n電源：雙向電源-太陽能和鋰電池 (1 × LR1130)\n鋰電池壽命：LR1130約3年（每天使用1小時）\n自動關機系統：大約每6分鐘自動關機\n尺寸(H × W × D mm)：19.4 × 85 × 120\n重量：約70 克 (含鋰電池)",
        "price": 300,
        "amount": 19,
        "fare": 30
    },
    {
        "id": 30,
        "buyer": "Ava",
        "status": "待出貨",
        "seller": "Brown（布朗）",
        "name": "【Transcend 創見】4TB StoreJet 25M3 軍規防震2.5吋USB3.1行動硬碟-太空灰 (TS4TSJ25M3S)",
        "typeId": 11,
        "type": "電腦與周邊配件",
        "subType": "儲存裝置",
        "item": "內接硬碟/外接硬碟",
        "picture": "ID53.jpg",
        "description": "ID53D.jpg",
        "price": 3399,
        "amount": 5,
        "fare": 60
    },
    {
        "id": 31,
        "buyer": "Aurora",
        "status": "已出貨",
        "seller": "Edwards（愛德華茲）",
        "name": "【CASIO 】10位元繽紛馬卡龍色迷你型計算機-薄荷綠 (MS-7UC-GN)",
        "typeId": 31,
        "type": "文具、美術用具",
        "subType": "學校、辦公用品",
        "item": "計算器",
        "picture": "ID34.jpg",
        "description": "型號：MS-7UC-GN\n類型：迷你桌上型\n顯示：負數（-），常數（K），錯誤（E），功能命令符號，3位逗號標記，記憶（M），稅務計算符號（TAX+/TAX-），時間計算符號\n計算功能：基本四則計算操作，稅務計算，常數計算，利潤率百分比計算，近似計算，開方根計算，時間計算\n數字：10位數字\n記憶體：獨立記憶體，稅率計算記憶體\n電源：雙向電源-太陽能和鋰電池 (1 × LR1130)\n鋰電池壽命：LR1130約3年（每天使用1小時）\n自動關機系統：大約每6分鐘自動關機\n尺寸(H × W × D mm)：19.4 × 85 × 120\n重量：約70 克 (含鋰電池)",
        "price": 350,
        "amount": 13,
        "fare": 1
    },
    {
        "id": 32,
        "buyer": "Ava",
        "status": "待出貨",
        "seller": "Lewis（劉易斯）",
        "name": "ASUS_華碩S501MD系列 - i5處理器 - 8G記憶體\n512G SSD / 無作業系統電腦",
        "typeId": 1,
        "type": "電腦與周邊配件",
        "subType": "桌上型電腦",
        "item": "桌上型電腦",
        "picture": "ID216.jpg,ID216_2.jpg",
        "description": "處理器：Intel Core i5-12400\n主機板晶片組：Intel B660\n記憶體：8GB DDR4 = (8G x 1條)(Long-DIMM(U-DIMM) 記憶體支援容量 : 總插槽數量 2 / 最高容量64G)\n硬碟：512GB M.2 NVMe™ PCIe® 3.0 SSD(擴充SATA HDD需購買螺絲*)\n光碟機：DVD writer 8X\n讀卡機：無\n鍵鼠組：有\n音效：High Definition 7.1 Channel Audio\n螢幕輸出介面：D-Sub(VGA)．HDMI．DP\n無線網路：Wi-Fi 5(802.11ac) (Dual band) 1*1 + Bluetooth® 5.1 Wireless Card\n有線網路：Intel WGI219V 10/100/1000 GbE, non-vPro\n電源供應：300W power supply (peak 350W)\n作業系統：無\n保固：原廠三年保固/到府收送\n(免費第一年到府維修)\n(原廠於保固期內將自行或委託第三方到府收送)\n\n●前端介面\n1x Headphone\n1x MIC in\n2x USB 2.0 Type-A\n2x USB 3.2 Gen 1 Type-A\n\n●後端介面\n1x RJ45 Gigabit Ethernet\n1x HDMI 1.4\n1x VGA Port\n1x Display port 1.4\n2x PS2\n3 x Audio jacks\n2x USB 2.0 Type-A\n2x USB 3.2 Gen 1 Type-A\n\n●擴充介面(含已使用)\n4x SATA 6.0Gb/s ports\n1x PCIe® 4.0 x 16\n2x M.2 connector for storage\n1x PCIe® 4.0 x 16\n2x PCIe® 3.0 x 1\n1x M.2 connector for WiFi\n2x DDR4 U-DIMM slot\n\n體積:16.00 x 31.89 x 36.78 cm\n重量:5.90 kg",
        "price": 14900,
        "amount": 10,
        "fare": 1000
    },
    {
        "id": 33,
        "buyer": "Abigail",
        "status": "已出貨",
        "seller": "Clarke（克拉克）",
        "name": "TCELL 冠元 TC200 USB3.2/Type C Gen2x2 1TB 超速外接式固態硬碟SSD (深海藍)",
        "typeId": 11,
        "type": "電腦與周邊配件",
        "subType": "儲存裝置",
        "item": "內接硬碟/外接硬碟",
        "picture": "ID51.jpg",
        "description": "ID51D.jpg",
        "price": 3000,
        "amount": 8,
        "fare": 1
    },
    {
        "id": 34,
        "buyer": "Abbie",
        "status": "已出貨",
        "seller": "Lewis（劉易斯）",
        "name": "MSI_微星Infinite S3電競系列 - i5處理器 / 16G記憶體\n1TB SSD / RTX3050顯卡 / Win11家用版電腦 / 500瓦電源",
        "typeId": 1,
        "type": "電腦與周邊配件",
        "subType": "桌上型電腦",
        "item": "桌上型電腦",
        "picture": "ID306.jpg,ID306_2.jpg",
        "description": "型號：MAG Infinite S3 12BTA-1659TW-B51240F305616GS1TX11MHAH1\n處理器：Intel Core i5-12400F\n主機板晶片組：Intel H610\n記憶體：16GB  DDR5  (16Gx1) / 2 x DDR5 U-DIMMs,up to 64GB\n固態硬碟：1TB*1 M.2 PCIE GEN3\n顯示卡：GeForce RTX 3050 VENTUS 2X,6G\n光碟機：無\n音效：7.1 Channel HD Audio (ALC897)\n無線網路：Intel Wi-Fi 6E AX210 /　藍牙 5.2\n有線網路：Intel  I219V\n電源供應：500W Bronze 80 Plus (ATX)\nCOOLING SYSTEM：Air Cooler\n作業系統：Windows 11 Home\n\n●前端介面\n1 x USB 3.2 Gen 1 Type C\n1 x 麥克風輸入\n1 x 耳機輸出 \n\n●後端介面\n2 x USB 3.2 Gen 1 Type A\n4 x USB 2.0 Type A\n1 x RJ45\n1 x PS/2\n3 x Audio jacks\n2 x HDMI\n1 x DP\n\n尺寸：173.8 x 446.97 x 407.17 mm\n體積：32 Liters\n重量：機器7.73KG，含外箱10.44KG\n\n保固：\n台灣地區3年保固\n台灣地區3年到府收送\n免費客服電話0800-018880",
        "price": 28000,
        "amount": 5,
        "fare": 1
    },
    {
        "id": 35,
        "buyer": "Ada",
        "status": "已收貨",
        "seller": "Hughes（休斯）",
        "name": "KINYO 藍牙5.0無線音箱 立體環繞360讀卡喇叭音響，支援藍芽/USB/TF卡/AUX，適用具藍牙功能或3.5mm插孔的平板電腦/筆記型電腦/智慧型手機",
        "typeId": 28,
        "type": "影音",
        "subType": "音響/喇叭",
        "item": "音響喇叭",
        "picture": "ID21.jpg",
        "description": "‧功能控制 藍牙/USB/TF卡/AUX\n‧介面 Bluetooth V5.0\n‧最大接收距離 10M(無任何障礙環境)\n‧輸出功率3W*2 (R.M.S.)\n‧額定電壓 USB DC 5V / 充電電池3.7V\n‧電池規格 聚合物鋰電池1200mAh\n‧消耗電流 200mA\n‧抗阻 4Ω\n‧噪音比 ≧80dB\n‧喇叭單體 2x40mm全音域喇叭\n‧響應頻率 120HZ-20KHz\n‧支援音樂格式MP3\n‧材質 塑料、金屬\n‧產品重量:618g\n‧產品尺寸:400x65x58(WxHxD)mm   \n‧配件 充電線x1、音源線x1",
        "price": 950,
        "amount": 12,
        "fare": 60
    },
    {
        "id": 36,
        "buyer": "Ava",
        "status": "已出貨",
        "seller": "Lewis（劉易斯）",
        "name": "ASUS_華碩S501MD系列 - i5處理器 - 16G記憶體\n1TB SSD / INTEL Arc A380顯卡 / Win11家用版電腦",
        "typeId": 1,
        "type": "電腦與周邊配件",
        "subType": "桌上型電腦",
        "item": "桌上型電腦",
        "picture": "ID66.jpg,ID66_2.jpg,ID66_3.jpg",
        "description": "處理器：Intel Core i5-12400F\n主機板晶片組：Intel B660\n記憶體：16GB DDR4 3200MHz = (16G x 1條)(Long-DIMM(U-DIMM) 記憶體支援容量 : 總插槽數量 2 / 最高容量64G)\n硬碟：1TB M.2 2280 NVMe™ PCIe® 3.0 SSD(擴充SATA HDD需購買螺絲*)\n顯示介面：INTEL® Arc™ A380 6GB GDDR6 : 3x DP, 1x HDMI\n光碟機：無\n讀卡機：無\n鍵鼠組：無\n音效：High Definition 7.1 Channel Audio\n螢幕輸出介面：HDMI．DP\n無線網路：Wi-Fi 5(802.11ac) (Dual band) 1*1 + Bluetooth® 5.1 Wireless Card\n有線網路：Intel WGI219V 10/100/1000 Mbps, non-vPro\n電源供應：300W power supply (80+ Bronze, peak 350W)\n作業系統：Windows 11 家用版 (64 bit)\n保固：原廠三年保固/到府收送\n(免費第一年到府維修)\n(原廠於保固期內將自行或委託第三方到府收送)\n\n●前端介面\n1x Headphone\n1x MIC in\n2x USB 2.0 Type-A\n2x USB 3.2 Gen 1 Type-A\n\n●後端介面\n1x RJ45 Gigabit Ethernet\n2x PS2\n3 x Audio jacks\n2x USB 2.0 Type-A\n2x USB 3.2 Gen 1 Type-A\n3x DP (位於顯卡)\n1x HDMI (位於顯卡)\n\n●擴充介面(含已使用)\n1x 3.5\"\n4x SATA 6.0Gb/s ports\n2x M.2 connector for storage\n1x PCIe® 4.0 x 16\n2x PCIe® 3.0 x 1\n1x M.2 connector for WiFi\n2x DDR4 U-DIMM slot\n\n體積:16.00 x 31.89 x 36.78 cm\n重量:5.90 kg",
        "price": 17990,
        "amount": 500,
        "fare": 1
    },
    {
        "id": 37,
        "buyer": "Ada",
        "status": "待出貨",
        "seller": "Hughes（休斯）",
        "name": "DIKE 鳴揚 多功能一體式藍牙喇叭 40W 替代劇院可遙控無線音響(DS606BK)",
        "typeId": 28,
        "type": "影音",
        "subType": "音響/喇叭",
        "item": "音響喇叭",
        "picture": "ID69.jpg",
        "description": "ID69D.jpg",
        "price": 2490,
        "amount": 19,
        "fare": 60
    },
    {
        "id": 38,
        "buyer": "Abigail",
        "status": "待出貨",
        "seller": "Edwards（愛德華茲）",
        "name": "【CASIO 】12位元繽紛馬卡龍色系便利型計算機-MS-20UC系列~原廠保固24個月",
        "typeId": 31,
        "type": "文具、美術用具",
        "subType": "學校、辦公用品",
        "item": "計算器",
        "picture": "ID1.jpg",
        "description": "■ MS-20UC\n■ 12位數 \n■ 獨立記憶體\n■ 百分比計算\n■ 利潤率計算\n■ 開根號計算 \n■ 正負數顯示\n■ 倒退鍵\n■ 千分位符號\n■ 時間計算 \n■ 稅金計算\n■ 太陽能和電池雙電力\n■ 長149.5*寬105*高22.8mm\n■ 重量110g",
        "price": 400,
        "amount": 13,
        "fare": 60
    },
    {
        "id": 39,
        "buyer": "Ava",
        "status": "已收貨",
        "seller": "Lewis（劉易斯）",
        "name": "ACER_宏碁XC-1760系列 - i3處理器 - 8G記憶體\n1T + 256G SSD / Win11家用版電腦",
        "typeId": 1,
        "type": "電腦與周邊配件",
        "subType": "桌上型電腦",
        "item": "桌上型電腦",
        "picture": "ID324.jpg,ID324_2.jpg",
        "description": "處理器：Intel Core i3-12100\n主機板晶片組：Intel H610\n記憶體：8GB DDR4 3200MHz = (8G x 1條)(Long-DIMM(U-DIMM) 記憶體支援容量 : 總插槽數量 2 / 最高容量32G)\n硬碟：1TB HDD 7.2K + 256G PCIe M.2 SSD(擴充SATA HDD需購買螺絲*)\n顯示介面：內建\n光碟機：無\n讀卡機：無\n鍵鼠組：有\n音效：Integrated high-definition, 5.1-channel surround sound\n螢幕輸出介面：HDMI\n無線網路：802.11 ax/ac/a/b/g/n, Wi-Fi 6 + Bluetooth® 5.0\n有線網路：RJ45\n電源供應：300W\n作業系統：Windows 11 家用版 (64 bit)\n保固：原廠三年保固/到府收送\n(原廠於保固期內將自行或委託第三方到府收送)  (宏碁家用)\n\n●前端介面\n1x USB 3.2 Gen 1 Type-C™\n1x USB 3.2 Gen 1 Type-A\n1x 3.5mm Headset/speaker jack\n1x Microphone jack\n\n●後端介面\n2x HDMI Port (out)\n4x USB 2.0 Type-A\n1x USB 3.2 Gen1 Type-A\n1x Audio jacks\n1x Ethernet (RJ-45) port\n1x Power connector\n\n體積:100 (W) x 330 (D) x 295 (H) mm",
        "price": 13900,
        "amount": 12,
        "fare": 1500
    },
    {
        "id": 40,
        "buyer": "Amelia",
        "status": "待出貨",
        "seller": "Patel（帕特爾）",
        "name": "ASUS_華碩S500TE系列 - i3處理器 - 8G記憶體\n512G SSD / 無作業系統電腦",
        "typeId": 3,
        "type": "電腦與周邊配件",
        "subType": "桌上型電腦",
        "item": "伺服器主機",
        "picture": "ID72.jpg,ID72_2.jpg",
        "description": "處理器：Intel Core i3-13100\n晶片：Intel B760\n記憶體：記憶體：8GB DDR4 3200MHz = (8G x 1條)(Long-DIMM(U-DIMM)記憶體支援容量 : 總插槽數量 2 / 最高容量64G)\n硬碟：512GB M.2 2280 NVMe™ PCIe® 4.0 SSD(擴充硬碟需自行購買螺絲)\n顯示介面：內顯\n光碟機：無\n讀卡機：無\n鍵鼠組：有\n音效：High Definition 7.1 Channel Audio\n螢幕輸出介面：D-Sub(VGA)．HDMI．DP\n無線網路：Wi-Fi 5(802.11ac) (Dual band) 1*1 + Bluetooth® 5.1 Wireless Card\n有線網路：Intel WGI219V 10/100/1000 Mbps, non-vPro\n電源供應：300W power supply (80+ Bronze, peak 350W)\n作業系統：無作業系統\n保固：原廠三年保固/到府收送\n(免費第一年到府維修)\n(原廠於保固期內將自行或委託第三方到府收送) \n\n●前端 I/O Port\t\n1x Headphone\n1x Mic in\n2x USB 2.0 Type-A\n2x USB 3.2 Gen 1 Type-A\n\n●後端 I/O Port\t\n1x RJ45 Gigabit Ethernet\n1x HDMI 1.4\n1x VGA Port\n1x Display port 1.4\n2x PS2\n3x Audio jacks\n2x USB 2.0 Type-A\n2x USB 3.2 Gen 1 Type-A\n\n●擴充槽(含已使用)\n2x 3.5\"\n4x SATA 6.0Gb/s ports\n2x M.2 connector for storage\n1x PCIe® 4.0 x 16\n2x PCIe® 3.0 x 1\n1x M.2 connector for WiFi\n2x DDR4 U-DIMM slot\n\n體積：17.60 x 39.30 x 38.50 cm (6.93\" x 15.47\" x 15.16\")\n重量：7.70 kg (16.98 lbs)",
        "price": 12618,
        "amount": 8,
        "fare": 1
    },
    {
        "id": 41,
        "buyer": "Anna",
        "status": "已出貨",
        "seller": "Clarke（克拉克）",
        "name": "【Transcend 創見】4TB StoreJet 25M3 軍規防震2.5吋USB3.1行動硬碟-太空灰 (TS4TSJ25M3S)",
        "typeId": 11,
        "type": "電腦與周邊配件",
        "subType": "儲存裝置",
        "item": "內接硬碟/外接硬碟",
        "picture": "ID53.jpg",
        "description": "ID53D.jpg",
        "price": 3399,
        "amount": 15,
        "fare": 1
    },
    {
        "id": 42,
        "buyer": "Abbie",
        "status": "已出貨",
        "seller": "Clarke（克拉克）",
        "name": "【Transcend 創見】2TB StoreJet 25C3S 極致輕薄2.5吋Type C行動硬碟 (TS2TSJ25C3S)",
        "typeId": 11,
        "type": "電腦與周邊配件",
        "subType": "儲存裝置",
        "item": "內接硬碟/外接硬碟",
        "picture": "ID74.jpg",
        "description": "ID74D.jpg",
        "price": 3087,
        "amount": 6,
        "fare": 30
    },
    {
        "id": 43,
        "buyer": "Ada",
        "status": "已收貨",
        "seller": "Hall（霍爾）",
        "name": "DIKE 鳴揚 多功能一體式藍牙喇叭 40W 替代劇院可遙控無線音響(DS606BK)",
        "typeId": 28,
        "type": "影音",
        "subType": "音響/喇叭",
        "item": "音響喇叭",
        "picture": "ID69.jpg",
        "description": "ID69D.jpg",
        "price": 2500,
        "amount": 8,
        "fare": 60
    },
    {
        "id": 44,
        "buyer": "Aurora",
        "status": "已收貨",
        "seller": "Edwards（愛德華茲）",
        "name": "【CASIO】12位數工程型計算機2代-(FX-991ESPLUS-2)",
        "typeId": 31,
        "type": "文具、美術用具",
        "subType": "學校、辦公用品",
        "item": "計算器",
        "picture": "ID39.jpg",
        "description": "數學自然顯示\n417個函數\n自然V.P.A.M. 顯示\n如同教科書般的顯示方式\n條列式統計資料編輯器\n多重重現顯示\n10 + 2位數\n新等式模式\n隨機整數\n分數計算\n組合與排列\n統計\n9個變數\n表格函數\n點矩陣顯示\n雙電源系統\n附帶硬式外殼\n尺寸：11.1x77x161.5mm\n重量：95g",
        "price": 850,
        "amount": 5,
        "fare": 60
    },
    {
        "id": 45,
        "buyer": "Ada",
        "status": "待出貨",
        "seller": "Green（格林）",
        "name": "DIKE 鳴揚 多功能一體式藍牙喇叭 40W 替代劇院可遙控無線音響(DS606BK)",
        "typeId": 28,
        "type": "影音",
        "subType": "音響/喇叭",
        "item": "音響喇叭",
        "picture": "ID69.jpg",
        "description": "ID69D.jpg",
        "price": 2500,
        "amount": 14,
        "fare": 30
    },
    {
        "id": 46,
        "buyer": "Alice",
        "status": "待出貨",
        "seller": "Patel（帕特爾）",
        "name": "ASUS_華碩S501MD系列 - i5處理器 - 16G記憶體\n1TB SSD / INTEL Arc A380顯卡 / Win11家用版電腦",
        "typeId": 1,
        "type": "電腦與周邊配件",
        "subType": "桌上型電腦",
        "item": "桌上型電腦",
        "picture": "ID81.jpg,ID81_2.jpg",
        "description": "處理器：Intel Core i5-12400F\n主機板晶片組：Intel B660\n記憶體：16GB DDR4 3200MHz = (16G x 1條)(Long-DIMM(U-DIMM) 記憶體支援容量 : 總插槽數量 2 / 最高容量64G)\n硬碟：1TB M.2 2280 NVMe™ PCIe® 3.0 SSD(擴充SATA HDD需購買螺絲*)\n顯示介面：INTEL® Arc™ A380 6GB GDDR6 : 3x DP, 1x HDMI\n光碟機：無\n讀卡機：無\n鍵鼠組：無\n音效：High Definition 7.1 Channel Audio\n螢幕輸出介面：HDMI．DP\n無線網路：Wi-Fi 5(802.11ac) (Dual band) 1*1 + Bluetooth® 5.1 Wireless Card\n有線網路：Intel WGI219V 10/100/1000 Mbps, non-vPro\n電源供應：300W power supply (80+ Bronze, peak 350W)\n作業系統：Windows 11 家用版 (64 bit)\n保固：原廠三年保固/到府收送\n(免費第一年到府維修)\n(原廠於保固期內將自行或委託第三方到府收送)\n\n●前端介面\n1x Headphone\n1x MIC in\n2x USB 2.0 Type-A\n2x USB 3.2 Gen 1 Type-A\n\n●後端介面\n1x RJ45 Gigabit Ethernet\n2x PS2\n3 x Audio jacks\n2x USB 2.0 Type-A\n2x USB 3.2 Gen 1 Type-A\n3x DP (位於顯卡)\n1x HDMI (位於顯卡)\n\n●擴充介面(含已使用)\n1x 3.5\"\n4x SATA 6.0Gb/s ports\n2x M.2 connector for storage\n1x PCIe® 4.0 x 16\n2x PCIe® 3.0 x 1\n1x M.2 connector for WiFi\n2x DDR4 U-DIMM slot\n\n體積:16.00 x 31.89 x 36.78 cm\n重量:5.90 kg",
        "price": 17990,
        "amount": 16,
        "fare": 60
    },
    {
        "id": 47,
        "buyer": "Aurora",
        "status": "完成訂單",
        "seller": "Brown（布朗）",
        "name": "【Transcend 創見】2TB StoreJet 25C3S 極致輕薄2.5吋Type C行動硬碟 (TS2TSJ25C3S)",
        "typeId": 11,
        "type": "電腦與周邊配件",
        "subType": "儲存裝置",
        "item": "內接硬碟/外接硬碟",
        "picture": "ID74.jpg",
        "description": "ID74D.jpg",
        "price": 2749,
        "amount": 20,
        "fare": 30
    },
    {
        "id": 48,
        "buyer": "Aria",
        "status": "已收貨",
        "seller": "Clarke（克拉克）",
        "name": "威剛ADATA HD710 PRO 4TB 2.5吋軍規硬碟-黑",
        "typeId": 11,
        "type": "電腦與周邊配件",
        "subType": "儲存裝置",
        "item": "內接硬碟/外接硬碟",
        "picture": "ID83.jpg",
        "description": "ID83D.jpg",
        "price": 3899,
        "amount": 15,
        "fare": 60
    },
    {
        "id": 49,
        "buyer": "Aria",
        "status": "完成訂單",
        "seller": "Jackson（傑克遜）",
        "name": "KINYO 藍牙5.0無線音箱 立體環繞360讀卡喇叭音響，支援藍芽/USB/TF卡/AUX，適用具藍牙功能或3.5mm插孔的平板電腦/筆記型電腦/智慧型手機",
        "typeId": 28,
        "type": "影音",
        "subType": "音響/喇叭",
        "item": "音響喇叭",
        "picture": "ID21.jpg",
        "description": "‧功能控制 藍牙/USB/TF卡/AUX\n‧介面 Bluetooth V5.0\n‧最大接收距離 10M(無任何障礙環境)\n‧輸出功率3W*2 (R.M.S.)\n‧額定電壓 USB DC 5V / 充電電池3.7V\n‧電池規格 聚合物鋰電池1200mAh\n‧消耗電流 200mA\n‧抗阻 4Ω\n‧噪音比 ≧80dB\n‧喇叭單體 2x40mm全音域喇叭\n‧響應頻率 120HZ-20KHz\n‧支援音樂格式MP3\n‧材質 塑料、金屬\n‧產品重量:618g\n‧產品尺寸:400x65x58(WxHxD)mm   \n‧配件 充電線x1、音源線x1",
        "price": 1000,
        "amount": 16,
        "fare": 60
    },
    {
        "id": 50,
        "buyer": "Abbie",
        "status": "完成訂單",
        "seller": "Patel（帕特爾）",
        "name": "ASUS_華碩S500TE系列 - i3處理器 - 8G記憶體\n512G SSD / Win11家用版電腦",
        "typeId": 1,
        "type": "電腦與周邊配件",
        "subType": "桌上型電腦",
        "item": "桌上型電腦",
        "picture": "ID85.jpg,ID85_2.jpg",
        "description": "處理器：Intel Core i3-13100\n晶片：Intel B760\n記憶體：記憶體：8GB DDR4 3200MHz = (8G x 1條)(Long-DIMM(U-DIMM)記憶體支援容量 : 總插槽數量 2 / 最高容量64G)\n硬碟：512GB M.2 2280 NVMe™ PCIe® 4.0 SSD(擴充硬碟需自行購買螺絲)\n顯示介面：內顯\n光碟機：無\n讀卡機：無\n鍵鼠組：有\n音效：High Definition 7.1 Channel Audio\n螢幕輸出介面：D-Sub(VGA)．HDMI．DP\n無線網路：Wi-Fi 5(802.11ac) (Dual band) 1*1 + Bluetooth® 5.1 Wireless Card\n有線網路：Intel WGI219V 10/100/1000 Mbps, non-vPro\n電源供應：300W power supply (80+ Bronze, peak 350W)\n作業系統：Windows 11 家用版 (64 bit)\n保固：原廠三年保固/到府收送\n(免費第一年到府維修)\n(原廠於保固期內將自行或委託第三方到府收送) \n\n●前端 I/O Port\t\n1x Headphone\n1x Mic in\n2x USB 2.0 Type-A\n2x USB 3.2 Gen 1 Type-A\n\n●後端 I/O Port\t\n1x RJ45 Gigabit Ethernet\n1x HDMI 1.4\n1x VGA Port\n1x Display port 1.4\n2x PS2\n3x Audio jacks\n2x USB 2.0 Type-A\n2x USB 3.2 Gen 1 Type-A\n\n●擴充槽(含已使用)\n2x 3.5\"\n4x SATA 6.0Gb/s ports\n2x M.2 connector for storage\n1x PCIe® 4.0 x 16\n2x PCIe® 3.0 x 1\n1x M.2 connector for WiFi\n2x DDR4 U-DIMM slot\n\n體積：17.60 x 39.30 x 38.50 cm (6.93\" x 15.47\" x 15.16\")\n重量：7.70 kg (16.98 lbs)",
        "price": 14618,
        "amount": 6,
        "fare": 1500
    },
    {
        "id": 51,
        "buyer": "Aurora",
        "status": "待出貨",
        "seller": "Edwards（愛德華茲）",
        "name": "卡西歐CASIO桌上型計算機/12位元/MX-12B",
        "typeId": 31,
        "type": "文具、美術用具",
        "subType": "學校、辦公用品",
        "item": "計算器",
        "picture": "ID86.jpg",
        "description": "ID86D.jpg",
        "price": 320,
        "amount": 10,
        "fare": 1
    },
    {
        "id": 52,
        "buyer": "Amelia",
        "status": "已收貨",
        "seller": "Evans（埃文斯）",
        "name": "【CASIO】12位數工程型計算機2代-(FX-991ESPLUS-2)",
        "typeId": 31,
        "type": "文具、美術用具",
        "subType": "學校、辦公用品",
        "item": "計算器",
        "picture": "ID39.jpg",
        "description": "數學自然顯示\n417個函數\n自然V.P.A.M. 顯示\n如同教科書般的顯示方式\n條列式統計資料編輯器\n多重重現顯示\n10 + 2位數\n新等式模式\n隨機整數\n分數計算\n組合與排列\n統計\n9個變數\n表格函數\n點矩陣顯示\n雙電源系統\n附帶硬式外殼\n尺寸：11.1x77x161.5mm\n重量：95g",
        "price": 870,
        "amount": 5,
        "fare": 60
    },
    {
        "id": 53,
        "buyer": "Aria",
        "status": "已收貨",
        "seller": "Brown（布朗）",
        "name": "威剛ADATA HD710 PRO 4TB 2.5吋軍規硬碟-黑",
        "typeId": 11,
        "type": "電腦與周邊配件",
        "subType": "儲存裝置",
        "item": "內接硬碟/外接硬碟",
        "picture": "ID83.jpg",
        "description": "ID83D.jpg",
        "price": 3899,
        "amount": 20,
        "fare": 60
    },
    {
        "id": 54,
        "buyer": "Abbie",
        "status": "已出貨",
        "seller": "Hall（霍爾）",
        "name": "小愛同學｜聲控家電｜您的智能管家",
        "typeId": 28,
        "type": "影音",
        "subType": "音響/喇叭",
        "item": "音響喇叭",
        "picture": "ID93.jpg",
        "description": "ID93D.jpg",
        "price": 890,
        "amount": 8,
        "fare": 30
    },
    {
        "id": 55,
        "buyer": "Aurora",
        "status": "已出貨",
        "seller": "Green（格林）",
        "name": "小愛同學｜聲控家電｜您的智能管家",
        "typeId": 28,
        "type": "影音",
        "subType": "音響/喇叭",
        "item": "音響喇叭",
        "picture": "ID93.jpg",
        "description": "ID93D.jpg",
        "price": 900,
        "amount": 13,
        "fare": 30
    },
    {
        "id": 56,
        "buyer": "Ariana",
        "status": "完成訂單",
        "seller": "Jackson（傑克遜）",
        "name": "DIKE 鳴揚 多功能一體式藍牙喇叭 40W 替代劇院可遙控無線音響(DS606BK)",
        "typeId": 28,
        "type": "影音",
        "subType": "音響/喇叭",
        "item": "音響喇叭",
        "picture": "ID69.jpg",
        "description": "ID69D.jpg",
        "price": 2450,
        "amount": 5,
        "fare": 60
    },
    {
        "id": 57,
        "buyer": "Abbie",
        "status": "已出貨",
        "seller": "Lewis（劉易斯）",
        "name": "ACER_宏碁XC-1760系列 - i5處理器 - 16G記憶體\n1TB SSD / Win11家用版電腦",
        "typeId": 1,
        "type": "電腦與周邊配件",
        "subType": "桌上型電腦",
        "item": "桌上型電腦",
        "picture": "ID368.jpg,ID368_2.jpg",
        "description": "●處理器：Intel Core i5-12400\n●晶片：H610\n●記憶體：16G DDR4 X 1 (記憶體支援容量 : 總插槽數量 2 / 最高容量32G)\n●儲存：1TB PCIe M.2 SSD\n●光碟機：無\n●讀卡機：無\n●音效：Integrated high-definition, 5.1-channel surround sound\n●無線網路：802.11 ax/ac/a/b/g/n, Wi-Fi 6\n●藍芽：Bluetooth® 5.0\n●電源：300W\n●作業系統：Windows 11 家用版 (64 bit)\n\n●前端 I/O Port\n1x USB 3.2 Gen 1 Type-C™\n1x USB 3.2 Gen 1 Type-A\n1x 3.5mm Headset/speaker jack\n1x Microphone jack\n\n●後端 I/O Port\n2x HDMI Port (out)\n4x USB 2.0 Type-A\n1x USB 3.2 Gen1 Type-A\n1x Audio jacks\n1x Ethernet (RJ-45) port\n1x Power connector\n\n體積:100 (W) x 330 (D) x 295 (H) mm\n保固：原廠三年保固/到府收送\n(原廠於保固期內將自行或委託第三方到府收送)",
        "price": 16900,
        "amount": 7,
        "fare": 1000
    },
    {
        "id": 58,
        "buyer": "Abbie",
        "status": "完成訂單",
        "seller": "Edwards（愛德華茲）",
        "name": "MY COLOR 點點膠水筆 (6入) 筆型點點膠 馬卡龍色 手帳黏膠 【F019】",
        "typeId": 34,
        "type": "文具、美術用具",
        "subType": "學校、辦公用品",
        "item": "膠水",
        "picture": "ID98.jpg",
        "description": "MY COLOR\n【商品規格】\n材質：塑料桿/水+樹脂\n規格：如圖所示\n(詳細尺寸請參考圖片±0.1~2cm)\n重量：53g",
        "price": 75,
        "amount": 15,
        "fare": 60
    },
    {
        "id": 59,
        "buyer": "Anna",
        "status": "完成訂單",
        "seller": "Clarke（克拉克）",
        "name": "Synology 群暉科技 DiskStation DS923+ (4Bay/AMD/4GB) NAS 網路儲存伺服器",
        "typeId": 13,
        "type": "電腦與周邊配件",
        "subType": "儲存裝置",
        "item": "NAS",
        "picture": "ID99.jpg",
        "description": "ID99D.jpg",
        "price": 18000,
        "amount": 10,
        "fare": 1
    },
    {
        "id": 60,
        "buyer": "Alice",
        "status": "待出貨",
        "seller": "Harris（哈里斯）",
        "name": "DIKE 鳴揚 多功能一體式藍牙喇叭 40W 替代劇院可遙控無線音響(DS606BK)",
        "typeId": 28,
        "type": "影音",
        "subType": "音響/喇叭",
        "item": "音響喇叭",
        "picture": "ID69.jpg",
        "description": "ID69D.jpg",
        "price": 2550,
        "amount": 10,
        "fare": 1
    },
    {
        "id": 61,
        "buyer": "Abbie",
        "status": "待出貨",
        "seller": "Jackson（傑克遜）",
        "name": "小愛同學｜聲控家電｜您的智能管家",
        "typeId": 28,
        "type": "影音",
        "subType": "音響/喇叭",
        "item": "音響喇叭",
        "picture": "ID93.jpg",
        "description": "ID93D.jpg",
        "price": 890,
        "amount": 12,
        "fare": 60
    },
    {
        "id": 62,
        "buyer": "Amelia",
        "status": "已出貨",
        "seller": "Clarke（克拉克）",
        "name": "Synology 群暉科技 DiskStation DS223 (2Bay/Realtek/2GB) NAS 網路儲存伺服器",
        "typeId": 13,
        "type": "電腦與周邊配件",
        "subType": "儲存裝置",
        "item": "NAS",
        "picture": "ID103.jpg",
        "description": "ID103D.jpg",
        "price": 8000,
        "amount": 13,
        "fare": 1
    },
    {
        "id": 63,
        "buyer": "Abbie",
        "status": "待出貨",
        "seller": "Harris（哈里斯）",
        "name": "小愛同學｜聲控家電｜您的智能管家",
        "typeId": 28,
        "type": "影音",
        "subType": "音響/喇叭",
        "item": "音響喇叭",
        "picture": "ID93.jpg",
        "description": "ID93D.jpg",
        "price": 890,
        "amount": 16,
        "fare": 30
    },
    {
        "id": 64,
        "buyer": "Anna",
        "status": "待出貨",
        "seller": "Evans（埃文斯）",
        "name": "【CASIO 】12位元繽紛馬卡龍色系便利型計算機-MS-20UC系列~原廠保固24個月",
        "typeId": 31,
        "type": "文具、美術用具",
        "subType": "學校、辦公用品",
        "item": "計算器",
        "picture": "ID1.jpg",
        "description": "■ MS-20UC\n■ 12位數 \n■ 獨立記憶體\n■ 百分比計算\n■ 利潤率計算\n■ 開根號計算 \n■ 正負數顯示\n■ 倒退鍵\n■ 千分位符號\n■ 時間計算 \n■ 稅金計算\n■ 太陽能和電池雙電力\n■ 長149.5*寬105*高22.8mm\n■ 重量110g",
        "price": 399,
        "amount": 6,
        "fare": 30
    },
    {
        "id": 65,
        "buyer": "Aurora",
        "status": "已收貨",
        "seller": "Davies（戴維斯）",
        "name": "【CASIO 】12位元繽紛馬卡龍色系便利型計算機-MS-20UC系列~原廠保固24個月",
        "typeId": 31,
        "type": "文具、美術用具",
        "subType": "學校、辦公用品",
        "item": "計算器",
        "picture": "ID1.jpg",
        "description": "■ MS-20UC\n■ 12位數 \n■ 獨立記憶體\n■ 百分比計算\n■ 利潤率計算\n■ 開根號計算 \n■ 正負數顯示\n■ 倒退鍵\n■ 千分位符號\n■ 時間計算 \n■ 稅金計算\n■ 太陽能和電池雙電力\n■ 長149.5*寬105*高22.8mm\n■ 重量110g",
        "price": 450,
        "amount": 8,
        "fare": 60
    },
    {
        "id": 66,
        "buyer": "Ann",
        "status": "已收貨",
        "seller": "Lewis（劉易斯）",
        "name": "ASUS_華碩S500TE系列 - i3處理器 - 8G記憶體\n512G SSD / Win11家用版電腦",
        "typeId": 1,
        "type": "電腦與周邊配件",
        "subType": "桌上型電腦",
        "item": "桌上型電腦",
        "picture": "ID41.jpg,ID41_2.jpg",
        "description": "規格說明\n處理器：Intel Core i3-13100\n晶片：Intel B760\n記憶體：記憶體：8GB DDR4 3200MHz = (8G x 1條)(Long-DIMM(U-DIMM)記憶體支援容量 : 總插槽數量 2 / 最高容量64G)\n硬碟：512GB M.2 2280 NVMe™ PCIe® 4.0 SSD(擴充硬碟需自行購買螺絲)\n顯示介面：內顯\n光碟機：無\n讀卡機：無\n鍵鼠組：有\n音效：High Definition 7.1 Channel Audio\n螢幕輸出介面：D-Sub(VGA)．HDMI．DP\n無線網路：Wi-Fi 5(802.11ac) (Dual band) 1*1 + Bluetooth® 5.1 Wireless Card\n有線網路：Intel WGI219V 10/100/1000 Mbps, non-vPro\n電源供應：300W power supply (80+ Bronze, peak 350W)\n作業系統：Windows 11 家用版 (64 bit)\n保固：原廠三年保固/到府收送\n(免費第一年到府維修)\n(原廠於保固期內將自行或委託第三方到府收送) \n\n●前端 I/O Port\t\n1x Headphone\n1x Mic in\n2x USB 2.0 Type-A\n2x USB 3.2 Gen 1 Type-A\n\n●後端 I/O Port\t\n1x RJ45 Gigabit Ethernet\n1x HDMI 1.4\n1x VGA Port\n1x Display port 1.4\n2x PS2\n3x Audio jacks\n2x USB 2.0 Type-A\n2x USB 3.2 Gen 1 Type-A\n\n●擴充槽(含已使用)\n2x 3.5\"\n4x SATA 6.0Gb/s ports\n2x M.2 connector for storage\n1x PCIe® 4.0 x 16\n2x PCIe® 3.0 x 1\n1x M.2 connector for WiFi\n2x DDR4 U-DIMM slot\n\n體積：17.60 x 39.30 x 38.50 cm (6.93\" x 15.47\" x 15.16\")\n重量：7.70 kg (16.98 lbs)",
        "price": 14000,
        "amount": 15,
        "fare": 1000
    },
    {
        "id": 67,
        "buyer": "Ada",
        "status": "待出貨",
        "seller": "Lewis（劉易斯）",
        "name": "ASUS_華碩S500TE系列 - i3處理器 - 8G記憶體\n512G SSD / 無作業系統電腦",
        "typeId": 1,
        "type": "電腦與周邊配件",
        "subType": "桌上型電腦",
        "item": "桌上型電腦",
        "picture": "ID72.jpg,ID72_2.jpg",
        "description": "處理器：Intel Core i3-13100\n晶片：Intel B760\n記憶體：記憶體：8GB DDR4 3200MHz = (8G x 1條)(Long-DIMM(U-DIMM)記憶體支援容量 : 總插槽數量 2 / 最高容量64G)\n硬碟：512GB M.2 2280 NVMe™ PCIe® 4.0 SSD(擴充硬碟需自行購買螺絲)\n顯示介面：內顯\n光碟機：無\n讀卡機：無\n鍵鼠組：有\n音效：High Definition 7.1 Channel Audio\n螢幕輸出介面：D-Sub(VGA)．HDMI．DP\n無線網路：Wi-Fi 5(802.11ac) (Dual band) 1*1 + Bluetooth® 5.1 Wireless Card\n有線網路：Intel WGI219V 10/100/1000 Mbps, non-vPro\n電源供應：300W power supply (80+ Bronze, peak 350W)\n作業系統：無作業系統\n保固：原廠三年保固/到府收送\n(免費第一年到府維修)\n(原廠於保固期內將自行或委託第三方到府收送) \n\n●前端 I/O Port\t\n1x Headphone\n1x Mic in\n2x USB 2.0 Type-A\n2x USB 3.2 Gen 1 Type-A\n\n●後端 I/O Port\t\n1x RJ45 Gigabit Ethernet\n1x HDMI 1.4\n1x VGA Port\n1x Display port 1.4\n2x PS2\n3x Audio jacks\n2x USB 2.0 Type-A\n2x USB 3.2 Gen 1 Type-A\n\n●擴充槽(含已使用)\n2x 3.5\"\n4x SATA 6.0Gb/s ports\n2x M.2 connector for storage\n1x PCIe® 4.0 x 16\n2x PCIe® 3.0 x 1\n1x M.2 connector for WiFi\n2x DDR4 U-DIMM slot\n\n體積：17.60 x 39.30 x 38.50 cm (6.93\" x 15.47\" x 15.16\")\n重量：7.70 kg (16.98 lbs)",
        "price": 12000,
        "amount": 8,
        "fare": 1
    },
    {
        "id": 68,
        "buyer": "Ariana",
        "status": "已收貨",
        "seller": "Patel（帕特爾）",
        "name": "MSI_微星13代i3四核心 獨顯\nMSI PRO DP180 i3-13100F/16G/1TB+512G SSD/P600_2G/500W/W11P",
        "typeId": 1,
        "type": "電腦與周邊配件",
        "subType": "桌上型電腦",
        "item": "桌上型電腦",
        "picture": "ID10.jpg",
        "description": "●主機主要規格\n．品牌：MSI 微星\n．主機型號：PRO DP180\n．晶片組：H610\n．處理器：Intel Core i3-13100F (4-Core, 12M Cache, 3.4GHz to 4.5GHz)\n．記憶體：16G DDR4\n．系統記憶體插槽數：2 個\n．記憶體最高支援容量：64GB\n．固態硬碟：512G M.2 PCIe SSD\n．傳統硬碟：1TB HDD\n．顯示功能類型：獨立顯示卡\n．顯示卡型號：已加裝NVIDIA Quadro P600 2G GDDR5 (三年保固 特仕升級) \n．顯示卡記憶體類型：GDDR5 \n．顯示卡記憶體容量：2G \n．光碟機：無\n．作業系統：Windows 11 Pro\n．主機型態：一般桌上型\n●其他規格\n．音效裝置：Realtek ALC897, 7.1 Channel HD Audio\n．區域網路：2.5G+1G LAN (Intel I226-V+Intel I219-V)\n．無線網路：Wi-Fi 6E\n．藍牙：Bluetooth 5.3\n．電源供應器：500W, 80PLUS BRONZE, ATX, POWER SUPPLY\n．鍵鼠組：無\n●前端面板\n．1x Headphone-out\n．1x Mic-in\n．2x Type A USB 3.2 Gen 1 \n．1x Type C USB 3.2 Gen 2 \n．1x Card Reader (SD & Micros SD card support)\n●後端面板\n．2x Type A USB 2.0\n．1x PS/2\n．1x Type A USB 3.2 Gen 1\n．1x 2.5G LAN\n．2x Type A USB 2.0 \n．1x RJ45 LAN (1G)\n．3x Audio Jacks\n．1x Padlock 機箱掛鎖\n．1x COM Port \n．1x Kensington Lock 防盜鎖孔\n●視訊面板\n．4 x Mini DisplayPort \n●機殼規格\n．尺寸：168 x 323 x 369mm\n．重量：5Kg以上\n●注意事項\n．保固說明：三年保固 (到府收送)\n．本商品不含螢幕傳輸線、螢幕轉接頭，請另外購買\n．此機原廠保固：不包含加裝記憶體、硬碟、顯示卡《由代理商保固》",
        "price": 29900,
        "amount": 7,
        "fare": 1
    },
    {
        "id": 69,
        "buyer": "Aria",
        "status": "待出貨",
        "seller": "Harris（哈里斯）",
        "name": "KINYO 藍芽4.2多功能無線接收器 適用 iPhone Xr, Xs, Xs Max, HTC U12 等無 3.5mm孔手機, 及車用喇叭 音響 有線耳機 藍芽接受器",
        "typeId": 28,
        "type": "影音",
        "subType": "音響/喇叭",
        "item": "音響喇叭",
        "picture": "ID11.jpg",
        "description": "◆4.2藍牙技術，天線效率有效最佳化，強化通訊能力。\n◆原音重現，高保真技術，不因無線化而影響最佳音質。\n◆大容量電池，可邊充電邊用，超長使用時間，不須擔心沒電斷訊。\n◆內建TF卡槽，可讀取Micro SD記憶卡內建音樂\n◆具來電接聽/掛斷，音量調整，播放/暫停，上/下曲切換功能。\n◆內建夾扣，不論何時，皆可夾上衣服使用。",
        "price": 499,
        "amount": 14,
        "fare": 30
    },
    {
        "id": 70,
        "buyer": "Abigail",
        "status": "已收貨",
        "seller": "Davies（戴維斯）",
        "name": "CASIO 12位數金屬面板計算機-黑灰色MX-120B",
        "typeId": 31,
        "type": "文具、美術用具",
        "subType": "學校、辦公用品",
        "item": "計算器",
        "picture": "ID12.jpg",
        "description": "ID12D.jpg",
        "price": 360,
        "amount": 8,
        "fare": 60
    },
    {
        "id": 71,
        "buyer": "Alice",
        "status": "已收貨",
        "seller": "Green（格林）",
        "name": "KINYO 藍芽4.2多功能無線接收器 適用 iPhone Xr, Xs, Xs Max, HTC U12 等無 3.5mm孔手機, 及車用喇叭 音響 有線耳機 藍芽接受器",
        "typeId": 28,
        "type": "影音",
        "subType": "音響/喇叭",
        "item": "音響喇叭",
        "picture": "ID11.jpg",
        "description": "◆4.2藍牙技術，天線效率有效最佳化，強化通訊能力。\n◆原音重現，高保真技術，不因無線化而影響最佳音質。\n◆大容量電池，可邊充電邊用，超長使用時間，不須擔心沒電斷訊。\n◆內建TF卡槽，可讀取Micro SD記憶卡內建音樂\n◆具來電接聽/掛斷，音量調整，播放/暫停，上/下曲切換功能。\n◆內建夾扣，不論何時，皆可夾上衣服使用。",
        "price": 550,
        "amount": 5,
        "fare": 60
    },
    {
        "id": 72,
        "buyer": "Alice",
        "status": "已收貨",
        "seller": "Edwards（愛德華茲）",
        "name": "CASIO 12位數金屬面板計算機-黑灰色MX-120B",
        "typeId": 31,
        "type": "文具、美術用具",
        "subType": "學校、辦公用品",
        "item": "計算器",
        "picture": "ID12.jpg",
        "description": "ID12D.jpg",
        "price": 300,
        "amount": 16,
        "fare": 30
    },
    {
        "id": 73,
        "buyer": "Amelia",
        "status": "待出貨",
        "seller": "Lewis（劉易斯）",
        "name": "ASUS_華碩S501MD系列 - i5處理器 - 16G記憶體\n1TB SSD / INTEL Arc A380顯卡 / Win11家用版電腦",
        "typeId": 1,
        "type": "電腦與周邊配件",
        "subType": "桌上型電腦",
        "item": "桌上型電腦",
        "picture": "ID81.jpg,ID81_2.jpg",
        "description": "處理器：Intel Core i5-12400F\n主機板晶片組：Intel B660\n記憶體：16GB DDR4 3200MHz = (16G x 1條)(Long-DIMM(U-DIMM) 記憶體支援容量 : 總插槽數量 2 / 最高容量64G)\n硬碟：1TB M.2 2280 NVMe™ PCIe® 3.0 SSD(擴充SATA HDD需購買螺絲*)\n顯示介面：INTEL® Arc™ A380 6GB GDDR6 : 3x DP, 1x HDMI\n光碟機：無\n讀卡機：無\n鍵鼠組：無\n音效：High Definition 7.1 Channel Audio\n螢幕輸出介面：HDMI．DP\n無線網路：Wi-Fi 5(802.11ac) (Dual band) 1*1 + Bluetooth® 5.1 Wireless Card\n有線網路：Intel WGI219V 10/100/1000 Mbps, non-vPro\n電源供應：300W power supply (80+ Bronze, peak 350W)\n作業系統：Windows 11 家用版 (64 bit)\n保固：原廠三年保固/到府收送\n(免費第一年到府維修)\n(原廠於保固期內將自行或委託第三方到府收送)\n\n●前端介面\n1x Headphone\n1x MIC in\n2x USB 2.0 Type-A\n2x USB 3.2 Gen 1 Type-A\n\n●後端介面\n1x RJ45 Gigabit Ethernet\n2x PS2\n3 x Audio jacks\n2x USB 2.0 Type-A\n2x USB 3.2 Gen 1 Type-A\n3x DP (位於顯卡)\n1x HDMI (位於顯卡)\n\n●擴充介面(含已使用)\n1x 3.5\"\n4x SATA 6.0Gb/s ports\n2x M.2 connector for storage\n1x PCIe® 4.0 x 16\n2x PCIe® 3.0 x 1\n1x M.2 connector for WiFi\n2x DDR4 U-DIMM slot\n\n體積:16.00 x 31.89 x 36.78 cm\n重量:5.90 kg",
        "price": 17990,
        "amount": 16,
        "fare": 1500
    },
    {
        "id": 74,
        "buyer": "Anna",
        "status": "待出貨",
        "seller": "Green（格林）",
        "name": "KINYO 藍牙5.0無線音箱 立體環繞360讀卡喇叭音響，支援藍芽/USB/TF卡/AUX，適用具藍牙功能或3.5mm插孔的平板電腦/筆記型電腦/智慧型手機",
        "typeId": 28,
        "type": "影音",
        "subType": "音響/喇叭",
        "item": "音響喇叭",
        "picture": "ID21.jpg",
        "description": "‧功能控制 藍牙/USB/TF卡/AUX\n‧介面 Bluetooth V5.0\n‧最大接收距離 10M(無任何障礙環境)\n‧輸出功率3W*2 (R.M.S.)\n‧額定電壓 USB DC 5V / 充電電池3.7V\n‧電池規格 聚合物鋰電池1200mAh\n‧消耗電流 200mA\n‧抗阻 4Ω\n‧噪音比 ≧80dB\n‧喇叭單體 2x40mm全音域喇叭\n‧響應頻率 120HZ-20KHz\n‧支援音樂格式MP3\n‧材質 塑料、金屬\n‧產品重量:618g\n‧產品尺寸:400x65x58(WxHxD)mm   \n‧配件 充電線x1、音源線x1",
        "price": 899,
        "amount": 6,
        "fare": 60
    },
    {
        "id": 75,
        "buyer": "Abbie",
        "status": "已收貨",
        "seller": "Lewis（劉易斯）",
        "name": "ASUS_華碩S500TE系列 - i3處理器 - 8G記憶體\n512G SSD / Win11家用版電腦",
        "typeId": 1,
        "type": "電腦與周邊配件",
        "subType": "桌上型電腦",
        "item": "桌上型電腦",
        "picture": "ID85.jpg,ID85_2.jpg",
        "description": "處理器：Intel Core i3-13100\n晶片：Intel B760\n記憶體：記憶體：8GB DDR4 3200MHz = (8G x 1條)(Long-DIMM(U-DIMM)記憶體支援容量 : 總插槽數量 2 / 最高容量64G)\n硬碟：512GB M.2 2280 NVMe™ PCIe® 4.0 SSD(擴充硬碟需自行購買螺絲)\n顯示介面：內顯\n光碟機：無\n讀卡機：無\n鍵鼠組：有\n音效：High Definition 7.1 Channel Audio\n螢幕輸出介面：D-Sub(VGA)．HDMI．DP\n無線網路：Wi-Fi 5(802.11ac) (Dual band) 1*1 + Bluetooth® 5.1 Wireless Card\n有線網路：Intel WGI219V 10/100/1000 Mbps, non-vPro\n電源供應：300W power supply (80+ Bronze, peak 350W)\n作業系統：Windows 11 家用版 (64 bit)\n保固：原廠三年保固/到府收送\n(免費第一年到府維修)\n(原廠於保固期內將自行或委託第三方到府收送) \n\n●前端 I/O Port\t\n1x Headphone\n1x Mic in\n2x USB 2.0 Type-A\n2x USB 3.2 Gen 1 Type-A\n\n●後端 I/O Port\t\n1x RJ45 Gigabit Ethernet\n1x HDMI 1.4\n1x VGA Port\n1x Display port 1.4\n2x PS2\n3x Audio jacks\n2x USB 2.0 Type-A\n2x USB 3.2 Gen 1 Type-A\n\n●擴充槽(含已使用)\n2x 3.5\"\n4x SATA 6.0Gb/s ports\n2x M.2 connector for storage\n1x PCIe® 4.0 x 16\n2x PCIe® 3.0 x 1\n1x M.2 connector for WiFi\n2x DDR4 U-DIMM slot\n\n體積：17.60 x 39.30 x 38.50 cm (6.93\" x 15.47\" x 15.16\")\n重量：7.70 kg (16.98 lbs)",
        "price": 14618,
        "amount": 6,
        "fare": 1000
    },
    {
        "id": 76,
        "buyer": "Amelia",
        "status": "完成訂單",
        "seller": "Brown（布朗）",
        "name": "WD_威騰WD_BLACK D10 Game Drive 8TB 3.5吋電競外接式硬碟(WDBA3P0080HBK-SESN)",
        "typeId": 11,
        "type": "電腦與周邊配件",
        "subType": "儲存裝置",
        "item": "內接硬碟/外接硬碟",
        "picture": "ID26.jpg",
        "description": "ID26D.jpg",
        "price": 7590,
        "amount": 15,
        "fare": 100
    },
    {
        "id": 77,
        "buyer": "Abigail",
        "status": "已出貨",
        "seller": "Clarke（克拉克）",
        "name": "WD_威騰WD_BLACK D10 Game Drive 8TB 3.5吋電競外接式硬碟(WDBA3P0080HBK-SESN)",
        "typeId": 11,
        "type": "電腦與周邊配件",
        "subType": "儲存裝置",
        "item": "內接硬碟/外接硬碟",
        "picture": "ID26.jpg",
        "description": "ID26D.jpg",
        "price": 8000,
        "amount": 15,
        "fare": 100
    },
    {
        "id": 78,
        "buyer": "Aurora",
        "status": "已收貨",
        "seller": "Jackson（傑克遜）",
        "name": "KINYO 藍芽4.2多功能無線接收器 適用 iPhone Xr, Xs, Xs Max, HTC U12 等無 3.5mm孔手機, 及車用喇叭 音響 有線耳機 藍芽接受器",
        "typeId": 28,
        "type": "影音",
        "subType": "音響/喇叭",
        "item": "音響喇叭",
        "picture": "ID11.jpg",
        "description": "◆4.2藍牙技術，天線效率有效最佳化，強化通訊能力。\n◆原音重現，高保真技術，不因無線化而影響最佳音質。\n◆大容量電池，可邊充電邊用，超長使用時間，不須擔心沒電斷訊。\n◆內建TF卡槽，可讀取Micro SD記憶卡內建音樂\n◆具來電接聽/掛斷，音量調整，播放/暫停，上/下曲切換功能。\n◆內建夾扣，不論何時，皆可夾上衣服使用。",
        "price": 600,
        "amount": 17,
        "fare": 30
    },
    {
        "id": 79,
        "buyer": "Aurora",
        "status": "已收貨",
        "seller": "Brown（布朗）",
        "name": "WD My Passport 4TB 2.5吋行動硬碟-藍(WDBPKJ0040BBL-WESN)",
        "typeId": 11,
        "type": "電腦與周邊配件",
        "subType": "儲存裝置",
        "item": "內接硬碟/外接硬碟",
        "picture": "ID32.jpg",
        "description": "ID32D.jpg",
        "price": 3190,
        "amount": 20,
        "fare": 60
    },
    {
        "id": 80,
        "buyer": "Alice",
        "status": "已出貨",
        "seller": "Evans（埃文斯）",
        "name": "CASIO 12位數金屬面板計算機-黑灰色MX-120B",
        "typeId": 31,
        "type": "文具、美術用具",
        "subType": "學校、辦公用品",
        "item": "計算器",
        "picture": "ID12.jpg",
        "description": "ID12D.jpg",
        "price": 400,
        "amount": 5,
        "fare": 1
    },
    {
        "id": 81,
        "buyer": "Ariana",
        "status": "已收貨",
        "seller": "Davies（戴維斯）",
        "name": "【CASIO 】10位元繽紛馬卡龍色迷你型計算機-薄荷綠 (MS-7UC-GN)",
        "typeId": 31,
        "type": "文具、美術用具",
        "subType": "學校、辦公用品",
        "item": "計算器",
        "picture": "ID34.jpg",
        "description": "型號：MS-7UC-GN\n類型：迷你桌上型\n顯示：負數（-），常數（K），錯誤（E），功能命令符號，3位逗號標記，記憶（M），稅務計算符號（TAX+/TAX-），時間計算符號\n計算功能：基本四則計算操作，稅務計算，常數計算，利潤率百分比計算，近似計算，開方根計算，時間計算\n數字：10位數字\n記憶體：獨立記憶體，稅率計算記憶體\n電源：雙向電源-太陽能和鋰電池 (1 × LR1130)\n鋰電池壽命：LR1130約3年（每天使用1小時）\n自動關機系統：大約每6分鐘自動關機\n尺寸(H × W × D mm)：19.4 × 85 × 120\n重量：約70 克 (含鋰電池)",
        "price": 319,
        "amount": 14,
        "fare": 60
    },
    {
        "id": 82,
        "buyer": "Abbie",
        "status": "已出貨",
        "seller": "Clarke（克拉克）",
        "name": "WD My Passport 4TB 2.5吋行動硬碟-藍(WDBPKJ0040BBL-WESN)",
        "typeId": 11,
        "type": "電腦與周邊配件",
        "subType": "儲存裝置",
        "item": "內接硬碟/外接硬碟",
        "picture": "ID32.jpg",
        "description": "ID32D.jpg",
        "price": 3000,
        "amount": 11,
        "fare": 60
    },
    {
        "id": 83,
        "buyer": "Abbie",
        "status": "待出貨",
        "seller": "Hughes（休斯）",
        "name": "KINYO 藍芽4.2多功能無線接收器 適用 iPhone Xr, Xs, Xs Max, HTC U12 等無 3.5mm孔手機, 及車用喇叭 音響 有線耳機 藍芽接受器",
        "typeId": 28,
        "type": "影音",
        "subType": "音響/喇叭",
        "item": "音響喇叭",
        "picture": "ID11.jpg",
        "description": "◆4.2藍牙技術，天線效率有效最佳化，強化通訊能力。\n◆原音重現，高保真技術，不因無線化而影響最佳音質。\n◆大容量電池，可邊充電邊用，超長使用時間，不須擔心沒電斷訊。\n◆內建TF卡槽，可讀取Micro SD記憶卡內建音樂\n◆具來電接聽/掛斷，音量調整，播放/暫停，上/下曲切換功能。\n◆內建夾扣，不論何時，皆可夾上衣服使用。",
        "price": 500,
        "amount": 19,
        "fare": 1
    },
    {
        "id": 84,
        "buyer": "Amelia",
        "status": "完成訂單",
        "seller": "Davies（戴維斯）",
        "name": "【CASIO】12位數工程型計算機2代-(FX-991ESPLUS-2)",
        "typeId": 31,
        "type": "文具、美術用具",
        "subType": "學校、辦公用品",
        "item": "計算器",
        "picture": "ID39.jpg",
        "description": "數學自然顯示\n417個函數\n自然V.P.A.M. 顯示\n如同教科書般的顯示方式\n條列式統計資料編輯器\n多重重現顯示\n10 + 2位數\n新等式模式\n隨機整數\n分數計算\n組合與排列\n統計\n9個變數\n表格函數\n點矩陣顯示\n雙電源系統\n附帶硬式外殼\n尺寸：11.1x77x161.5mm\n重量：95g",
        "price": 799,
        "amount": 12,
        "fare": 1
    },
    {
        "id": 85,
        "buyer": "Aria",
        "status": "待出貨",
        "seller": "Patel（帕特爾）",
        "name": "ASUS_華碩S500TE系列 - i3處理器 - 8G記憶體\n512G SSD / Win11家用版電腦",
        "typeId": 1,
        "type": "電腦與周邊配件",
        "subType": "桌上型電腦",
        "item": "桌上型電腦",
        "picture": "ID41.jpg,ID41_2.jpg",
        "description": "規格說明\n處理器：Intel Core i3-13100\n晶片：Intel B760\n記憶體：記憶體：8GB DDR4 3200MHz = (8G x 1條)(Long-DIMM(U-DIMM)記憶體支援容量 : 總插槽數量 2 / 最高容量64G)\n硬碟：512GB M.2 2280 NVMe™ PCIe® 4.0 SSD(擴充硬碟需自行購買螺絲)\n顯示介面：內顯\n光碟機：無\n讀卡機：無\n鍵鼠組：有\n音效：High Definition 7.1 Channel Audio\n螢幕輸出介面：D-Sub(VGA)．HDMI．DP\n無線網路：Wi-Fi 5(802.11ac) (Dual band) 1*1 + Bluetooth® 5.1 Wireless Card\n有線網路：Intel WGI219V 10/100/1000 Mbps, non-vPro\n電源供應：300W power supply (80+ Bronze, peak 350W)\n作業系統：Windows 11 家用版 (64 bit)\n保固：原廠三年保固/到府收送\n(免費第一年到府維修)\n(原廠於保固期內將自行或委託第三方到府收送) \n\n●前端 I/O Port\t\n1x Headphone\n1x Mic in\n2x USB 2.0 Type-A\n2x USB 3.2 Gen 1 Type-A\n\n●後端 I/O Port\t\n1x RJ45 Gigabit Ethernet\n1x HDMI 1.4\n1x VGA Port\n1x Display port 1.4\n2x PS2\n3x Audio jacks\n2x USB 2.0 Type-A\n2x USB 3.2 Gen 1 Type-A\n\n●擴充槽(含已使用)\n2x 3.5\"\n4x SATA 6.0Gb/s ports\n2x M.2 connector for storage\n1x PCIe® 4.0 x 16\n2x PCIe® 3.0 x 1\n1x M.2 connector for WiFi\n2x DDR4 U-DIMM slot\n\n體積：17.60 x 39.30 x 38.50 cm (6.93\" x 15.47\" x 15.16\")\n重量：7.70 kg (16.98 lbs)",
        "price": 14618,
        "amount": 15,
        "fare": 500
    },
    {
        "id": 86,
        "buyer": "Abbie",
        "status": "待出貨",
        "seller": "Harris（哈里斯）",
        "name": "KINYO 藍牙5.0無線音箱 立體環繞360讀卡喇叭音響，支援藍芽/USB/TF卡/AUX，適用具藍牙功能或3.5mm插孔的平板電腦/筆記型電腦/智慧型手機",
        "typeId": 28,
        "type": "影音",
        "subType": "音響/喇叭",
        "item": "音響喇叭",
        "picture": "ID21.jpg",
        "description": "‧功能控制 藍牙/USB/TF卡/AUX\n‧介面 Bluetooth V5.0\n‧最大接收距離 10M(無任何障礙環境)\n‧輸出功率3W*2 (R.M.S.)\n‧額定電壓 USB DC 5V / 充電電池3.7V\n‧電池規格 聚合物鋰電池1200mAh\n‧消耗電流 200mA\n‧抗阻 4Ω\n‧噪音比 ≧80dB\n‧喇叭單體 2x40mm全音域喇叭\n‧響應頻率 120HZ-20KHz\n‧支援音樂格式MP3\n‧材質 塑料、金屬\n‧產品重量:618g\n‧產品尺寸:400x65x58(WxHxD)mm   \n‧配件 充電線x1、音源線x1",
        "price": 950,
        "amount": 20,
        "fare": 60
    },
    {
        "id": 87,
        "buyer": "Ariana",
        "status": "已收貨",
        "seller": "Lewis（劉易斯）",
        "name": "ASUS_華碩S500SE系列 - i5處理器 - 8G記憶體\n512G SSD / Win11家用版電腦",
        "typeId": 1,
        "type": "電腦與周邊配件",
        "subType": "桌上型電腦",
        "item": "桌上型電腦",
        "picture": "ID121.jpg,ID121_2.jpg",
        "description": "處理器：Intel Core i5-13400\n主機板晶片組：Intel B760\n記憶體：8GB DDR4 3200MHz = (8G x 1條)(Long-DIMM(U-DIMM) 記憶體支援容量 : 總插槽數量 2 / 最高容量64G)\n硬碟：512GB M.2 NVMe™ PCIe4.0 SSD(擴充硬碟需自行購買螺絲)\n顯示介面：內建\n光碟機：DVD writer 8X\n讀卡機：有\n鍵鼠組：有\n音效：High Definition 7.1 Channel Audio\n螢幕輸出介面：HDMI．D-Sub(VGA)\n無線網路：Wi-Fi 5(802.11ac) (Dual band) 1*1 + Bluetooth® 5.1 Wireless Card\n有線網路：Intel WGI219V 10/100/1000 GbE, non-vPro\n電源供應：300W power supply (80+ Platinum, peak 390W)\n作業系統：Windows 11 家用版 (64 bit)\n保固：原廠三年保固/到府收送\n(免費第一年到府維修)\n(原廠於保固期內將自行或委託第三方到府收送) \n\n●前端介面\n1x Headphone\n1x 3.5mm combo audio jack\n2x USB 3.2 Gen 1 Type-A\n2x USB 3.2 Gen 2 Type-A\n1x 2 in 1 card reader SD / MMC\n1x Smart card reader\n\n●後端介面\n1x Headphone out\n1x Line-in\n1x MIC in\n1x RJ45 Gigabit Ethernet\n1x HDMI 1.4\n1x VGA Port\n2x PS2\n4x USB 2.0 Type-A\n\n●擴充介面(含已使用)\n1x 2.5\" 擴充槽 (可安裝儲存設備)\n1x 3.5\" 擴充槽 (可安裝儲存設備)\n4x SATA 6.0Gb/s ports\n1x PCIe® 4.0 x 16\n2x PCIe® 3.0 x 1\n1x M.2 connector for WiFi\n2x M.2 connector for storage\n2x DDR4 U-DIMM slot\n\n體積:09.46 x 29.27 x 33.96 cm (3.72\" x 11.52\" x 13.37\")\n重量:05.00 kg (11.02 lbs)",
        "price": 19990,
        "amount": 15,
        "fare": 1500
    },
    {
        "id": 88,
        "buyer": "Aria",
        "status": "已收貨",
        "seller": "Hall（霍爾）",
        "name": "KINYO 藍芽4.2多功能無線接收器 適用 iPhone Xr, Xs, Xs Max, HTC U12 等無 3.5mm孔手機, 及車用喇叭 音響 有線耳機 藍芽接受器",
        "typeId": 28,
        "type": "影音",
        "subType": "音響/喇叭",
        "item": "音響喇叭",
        "picture": "ID11.jpg",
        "description": "◆4.2藍牙技術，天線效率有效最佳化，強化通訊能力。\n◆原音重現，高保真技術，不因無線化而影響最佳音質。\n◆大容量電池，可邊充電邊用，超長使用時間，不須擔心沒電斷訊。\n◆內建TF卡槽，可讀取Micro SD記憶卡內建音樂\n◆具來電接聽/掛斷，音量調整，播放/暫停，上/下曲切換功能。\n◆內建夾扣，不論何時，皆可夾上衣服使用。",
        "price": 580,
        "amount": 20,
        "fare": 30
    },
    {
        "id": 89,
        "buyer": "Ann",
        "status": "完成訂單",
        "seller": "Lewis（劉易斯）",
        "name": "ASUS_華碩S500TE系列 - i3處理器 - 8G記憶體\n512G SSD / 無作業系統電腦",
        "typeId": 1,
        "type": "電腦與周邊配件",
        "subType": "桌上型電腦",
        "item": "桌上型電腦",
        "picture": "ID163.jpg,ID163_2.jpg",
        "description": "處理器：Intel Core i3-13100\n晶片：Intel B760\n記憶體：記憶體：8GB DDR4 3200MHz = (8G x 1條)(Long-DIMM(U-DIMM)記憶體支援容量 : 總插槽數量 2 / 最高容量64G)\n硬碟：512GB M.2 2280 NVMe™ PCIe® 4.0 SSD(擴充硬碟需自行購買螺絲)\n顯示介面：內顯\n光碟機：無\n讀卡機：無\n鍵鼠組：有\n音效：High Definition 7.1 Channel Audio\n螢幕輸出介面：D-Sub(VGA)．HDMI．DP\n無線網路：Wi-Fi 5(802.11ac) (Dual band) 1*1 + Bluetooth® 5.1 Wireless Card\n有線網路：Intel WGI219V 10/100/1000 Mbps, non-vPro\n電源供應：300W power supply (80+ Bronze, peak 350W)\n作業系統：無作業系統\n保固：原廠三年保固/到府收送\n(免費第一年到府維修)\n(原廠於保固期內將自行或委託第三方到府收送) \n\n●前端 I/O Port\t\n1x Headphone\n1x Mic in\n2x USB 2.0 Type-A\n2x USB 3.2 Gen 1 Type-A\n\n●後端 I/O Port\t\n1x RJ45 Gigabit Ethernet\n1x HDMI 1.4\n1x VGA Port\n1x Display port 1.4\n2x PS2\n3x Audio jacks\n2x USB 2.0 Type-A\n2x USB 3.2 Gen 1 Type-A\n\n●擴充槽(含已使用)\n2x 3.5\"\n4x SATA 6.0Gb/s ports\n2x M.2 connector for storage\n1x PCIe® 4.0 x 16\n2x PCIe® 3.0 x 1\n1x M.2 connector for WiFi\n2x DDR4 U-DIMM slot\n\n體積：17.60 x 39.30 x 38.50 cm (6.93\" x 15.47\" x 15.16\")\n重量：7.70 kg (16.98 lbs)",
        "price": 12618,
        "amount": 19,
        "fare": 1
    },
    {
        "id": 90,
        "buyer": "Aria",
        "status": "已出貨",
        "seller": "Hall（霍爾）",
        "name": "KINYO 藍牙5.0無線音箱 立體環繞360讀卡喇叭音響，支援藍芽/USB/TF卡/AUX，適用具藍牙功能或3.5mm插孔的平板電腦/筆記型電腦/智慧型手機",
        "typeId": 28,
        "type": "影音",
        "subType": "音響/喇叭",
        "item": "音響喇叭",
        "picture": "ID21.jpg",
        "description": "‧功能控制 藍牙/USB/TF卡/AUX\n‧介面 Bluetooth V5.0\n‧最大接收距離 10M(無任何障礙環境)\n‧輸出功率3W*2 (R.M.S.)\n‧額定電壓 USB DC 5V / 充電電池3.7V\n‧電池規格 聚合物鋰電池1200mAh\n‧消耗電流 200mA\n‧抗阻 4Ω\n‧噪音比 ≧80dB\n‧喇叭單體 2x40mm全音域喇叭\n‧響應頻率 120HZ-20KHz\n‧支援音樂格式MP3\n‧材質 塑料、金屬\n‧產品重量:618g\n‧產品尺寸:400x65x58(WxHxD)mm   \n‧配件 充電線x1、音源線x1",
        "price": 1000,
        "amount": 5,
        "fare": 30
    },
    {
        "id": 91,
        "buyer": "Aurora",
        "status": "完成訂單",
        "seller": "Brown（布朗）",
        "name": "TCELL 冠元 TC200 USB3.2/Type C Gen2x2 1TB 超速外接式固態硬碟SSD (深海藍)",
        "typeId": 11,
        "type": "電腦與周邊配件",
        "subType": "儲存裝置",
        "item": "內接硬碟/外接硬碟",
        "picture": "ID51.jpg",
        "description": "ID51D.jpg",
        "price": 2999,
        "amount": 19,
        "fare": 1
    },
    {
        "id": 92,
        "buyer": "Aurora",
        "status": "完成訂單",
        "seller": "Evans（埃文斯）",
        "name": "【CASIO 】10位元繽紛馬卡龍色迷你型計算機-薄荷綠 (MS-7UC-GN)",
        "typeId": 31,
        "type": "文具、美術用具",
        "subType": "學校、辦公用品",
        "item": "計算器",
        "picture": "ID34.jpg",
        "description": "型號：MS-7UC-GN\n類型：迷你桌上型\n顯示：負數（-），常數（K），錯誤（E），功能命令符號，3位逗號標記，記憶（M），稅務計算符號（TAX+/TAX-），時間計算符號\n計算功能：基本四則計算操作，稅務計算，常數計算，利潤率百分比計算，近似計算，開方根計算，時間計算\n數字：10位數字\n記憶體：獨立記憶體，稅率計算記憶體\n電源：雙向電源-太陽能和鋰電池 (1 × LR1130)\n鋰電池壽命：LR1130約3年（每天使用1小時）\n自動關機系統：大約每6分鐘自動關機\n尺寸(H × W × D mm)：19.4 × 85 × 120\n重量：約70 克 (含鋰電池)",
        "price": 300,
        "amount": 19,
        "fare": 30
    },
    {
        "id": 93,
        "buyer": "Amelia",
        "status": "完成訂單",
        "seller": "Brown（布朗）",
        "name": "【Transcend 創見】4TB StoreJet 25M3 軍規防震2.5吋USB3.1行動硬碟-太空灰 (TS4TSJ25M3S)",
        "typeId": 11,
        "type": "電腦與周邊配件",
        "subType": "儲存裝置",
        "item": "內接硬碟/外接硬碟",
        "picture": "ID53.jpg",
        "description": "ID53D.jpg",
        "price": 3399,
        "amount": 5,
        "fare": 60
    },
    {
        "id": 94,
        "buyer": "Aria",
        "status": "待出貨",
        "seller": "Edwards（愛德華茲）",
        "name": "【CASIO 】10位元繽紛馬卡龍色迷你型計算機-薄荷綠 (MS-7UC-GN)",
        "typeId": 31,
        "type": "文具、美術用具",
        "subType": "學校、辦公用品",
        "item": "計算器",
        "picture": "ID34.jpg",
        "description": "型號：MS-7UC-GN\n類型：迷你桌上型\n顯示：負數（-），常數（K），錯誤（E），功能命令符號，3位逗號標記，記憶（M），稅務計算符號（TAX+/TAX-），時間計算符號\n計算功能：基本四則計算操作，稅務計算，常數計算，利潤率百分比計算，近似計算，開方根計算，時間計算\n數字：10位數字\n記憶體：獨立記憶體，稅率計算記憶體\n電源：雙向電源-太陽能和鋰電池 (1 × LR1130)\n鋰電池壽命：LR1130約3年（每天使用1小時）\n自動關機系統：大約每6分鐘自動關機\n尺寸(H × W × D mm)：19.4 × 85 × 120\n重量：約70 克 (含鋰電池)",
        "price": 350,
        "amount": 13,
        "fare": 1
    },
    {
        "id": 95,
        "buyer": "Abbie",
        "status": "完成訂單",
        "seller": "Lewis（劉易斯）",
        "name": "ASUS_華碩S501MD系列 - i5處理器 - 8G記憶體\n512G SSD / 無作業系統電腦",
        "typeId": 1,
        "type": "電腦與周邊配件",
        "subType": "桌上型電腦",
        "item": "桌上型電腦",
        "picture": "ID216.jpg,ID216_2.jpg",
        "description": "處理器：Intel Core i5-12400\n主機板晶片組：Intel B660\n記憶體：8GB DDR4 = (8G x 1條)(Long-DIMM(U-DIMM) 記憶體支援容量 : 總插槽數量 2 / 最高容量64G)\n硬碟：512GB M.2 NVMe™ PCIe® 3.0 SSD(擴充SATA HDD需購買螺絲*)\n光碟機：DVD writer 8X\n讀卡機：無\n鍵鼠組：有\n音效：High Definition 7.1 Channel Audio\n螢幕輸出介面：D-Sub(VGA)．HDMI．DP\n無線網路：Wi-Fi 5(802.11ac) (Dual band) 1*1 + Bluetooth® 5.1 Wireless Card\n有線網路：Intel WGI219V 10/100/1000 GbE, non-vPro\n電源供應：300W power supply (peak 350W)\n作業系統：無\n保固：原廠三年保固/到府收送\n(免費第一年到府維修)\n(原廠於保固期內將自行或委託第三方到府收送)\n\n●前端介面\n1x Headphone\n1x MIC in\n2x USB 2.0 Type-A\n2x USB 3.2 Gen 1 Type-A\n\n●後端介面\n1x RJ45 Gigabit Ethernet\n1x HDMI 1.4\n1x VGA Port\n1x Display port 1.4\n2x PS2\n3 x Audio jacks\n2x USB 2.0 Type-A\n2x USB 3.2 Gen 1 Type-A\n\n●擴充介面(含已使用)\n4x SATA 6.0Gb/s ports\n1x PCIe® 4.0 x 16\n2x M.2 connector for storage\n1x PCIe® 4.0 x 16\n2x PCIe® 3.0 x 1\n1x M.2 connector for WiFi\n2x DDR4 U-DIMM slot\n\n體積:16.00 x 31.89 x 36.78 cm\n重量:5.90 kg",
        "price": 14900,
        "amount": 10,
        "fare": 1000
    },
    {
        "id": 96,
        "buyer": "Aurora",
        "status": "已出貨",
        "seller": "Clarke（克拉克）",
        "name": "TCELL 冠元 TC200 USB3.2/Type C Gen2x2 1TB 超速外接式固態硬碟SSD (深海藍)",
        "typeId": 11,
        "type": "電腦與周邊配件",
        "subType": "儲存裝置",
        "item": "內接硬碟/外接硬碟",
        "picture": "ID51.jpg",
        "description": "ID51D.jpg",
        "price": 3000,
        "amount": 8,
        "fare": 1
    },
    {
        "id": 97,
        "buyer": "Ada",
        "status": "已收貨",
        "seller": "Lewis（劉易斯）",
        "name": "MSI_微星Infinite S3電競系列 - i5處理器 / 16G記憶體\n1TB SSD / RTX3050顯卡 / Win11家用版電腦 / 500瓦電源",
        "typeId": 1,
        "type": "電腦與周邊配件",
        "subType": "桌上型電腦",
        "item": "桌上型電腦",
        "picture": "ID306.jpg,ID306_2.jpg",
        "description": "型號：MAG Infinite S3 12BTA-1659TW-B51240F305616GS1TX11MHAH1\n處理器：Intel Core i5-12400F\n主機板晶片組：Intel H610\n記憶體：16GB  DDR5  (16Gx1) / 2 x DDR5 U-DIMMs,up to 64GB\n固態硬碟：1TB*1 M.2 PCIE GEN3\n顯示卡：GeForce RTX 3050 VENTUS 2X,6G\n光碟機：無\n音效：7.1 Channel HD Audio (ALC897)\n無線網路：Intel Wi-Fi 6E AX210 /　藍牙 5.2\n有線網路：Intel  I219V\n電源供應：500W Bronze 80 Plus (ATX)\nCOOLING SYSTEM：Air Cooler\n作業系統：Windows 11 Home\n\n●前端介面\n1 x USB 3.2 Gen 1 Type C\n1 x 麥克風輸入\n1 x 耳機輸出 \n\n●後端介面\n2 x USB 3.2 Gen 1 Type A\n4 x USB 2.0 Type A\n1 x RJ45\n1 x PS/2\n3 x Audio jacks\n2 x HDMI\n1 x DP\n\n尺寸：173.8 x 446.97 x 407.17 mm\n體積：32 Liters\n重量：機器7.73KG，含外箱10.44KG\n\n保固：\n台灣地區3年保固\n台灣地區3年到府收送\n免費客服電話0800-018880",
        "price": 28000,
        "amount": 5,
        "fare": 1
    },
    {
        "id": 98,
        "buyer": "Aria",
        "status": "完成訂單",
        "seller": "Hughes（休斯）",
        "name": "KINYO 藍牙5.0無線音箱 立體環繞360讀卡喇叭音響，支援藍芽/USB/TF卡/AUX，適用具藍牙功能或3.5mm插孔的平板電腦/筆記型電腦/智慧型手機",
        "typeId": 28,
        "type": "影音",
        "subType": "音響/喇叭",
        "item": "音響喇叭",
        "picture": "ID21.jpg",
        "description": "‧功能控制 藍牙/USB/TF卡/AUX\n‧介面 Bluetooth V5.0\n‧最大接收距離 10M(無任何障礙環境)\n‧輸出功率3W*2 (R.M.S.)\n‧額定電壓 USB DC 5V / 充電電池3.7V\n‧電池規格 聚合物鋰電池1200mAh\n‧消耗電流 200mA\n‧抗阻 4Ω\n‧噪音比 ≧80dB\n‧喇叭單體 2x40mm全音域喇叭\n‧響應頻率 120HZ-20KHz\n‧支援音樂格式MP3\n‧材質 塑料、金屬\n‧產品重量:618g\n‧產品尺寸:400x65x58(WxHxD)mm   \n‧配件 充電線x1、音源線x1",
        "price": 950,
        "amount": 12,
        "fare": 60
    },
    {
        "id": 99,
        "buyer": "Aria",
        "status": "待出貨",
        "seller": "Lewis（劉易斯）",
        "name": "ASUS_華碩S501MD系列 - i5處理器 - 16G記憶體\n1TB SSD / INTEL Arc A380顯卡 / Win11家用版電腦",
        "typeId": 1,
        "type": "電腦與周邊配件",
        "subType": "桌上型電腦",
        "item": "桌上型電腦",
        "picture": "ID66.jpg,ID66_2.jpg,ID66_3.jpg",
        "description": "處理器：Intel Core i5-12400F\n主機板晶片組：Intel B660\n記憶體：16GB DDR4 3200MHz = (16G x 1條)(Long-DIMM(U-DIMM) 記憶體支援容量 : 總插槽數量 2 / 最高容量64G)\n硬碟：1TB M.2 2280 NVMe™ PCIe® 3.0 SSD(擴充SATA HDD需購買螺絲*)\n顯示介面：INTEL® Arc™ A380 6GB GDDR6 : 3x DP, 1x HDMI\n光碟機：無\n讀卡機：無\n鍵鼠組：無\n音效：High Definition 7.1 Channel Audio\n螢幕輸出介面：HDMI．DP\n無線網路：Wi-Fi 5(802.11ac) (Dual band) 1*1 + Bluetooth® 5.1 Wireless Card\n有線網路：Intel WGI219V 10/100/1000 Mbps, non-vPro\n電源供應：300W power supply (80+ Bronze, peak 350W)\n作業系統：Windows 11 家用版 (64 bit)\n保固：原廠三年保固/到府收送\n(免費第一年到府維修)\n(原廠於保固期內將自行或委託第三方到府收送)\n\n●前端介面\n1x Headphone\n1x MIC in\n2x USB 2.0 Type-A\n2x USB 3.2 Gen 1 Type-A\n\n●後端介面\n1x RJ45 Gigabit Ethernet\n2x PS2\n3 x Audio jacks\n2x USB 2.0 Type-A\n2x USB 3.2 Gen 1 Type-A\n3x DP (位於顯卡)\n1x HDMI (位於顯卡)\n\n●擴充介面(含已使用)\n1x 3.5\"\n4x SATA 6.0Gb/s ports\n2x M.2 connector for storage\n1x PCIe® 4.0 x 16\n2x PCIe® 3.0 x 1\n1x M.2 connector for WiFi\n2x DDR4 U-DIMM slot\n\n體積:16.00 x 31.89 x 36.78 cm\n重量:5.90 kg",
        "price": 17990,
        "amount": 500,
        "fare": 1
    },
    {
        "id": 100,
        "buyer": "Ann",
        "status": "已出貨",
        "seller": "Hughes（休斯）",
        "name": "DIKE 鳴揚 多功能一體式藍牙喇叭 40W 替代劇院可遙控無線音響(DS606BK)",
        "typeId": 28,
        "type": "影音",
        "subType": "音響/喇叭",
        "item": "音響喇叭",
        "picture": "ID69.jpg",
        "description": "ID69D.jpg",
        "price": 2490,
        "amount": 19,
        "fare": 60
    },
    {
        "id": 101,
        "buyer": "Abbie",
        "status": "已出貨",
        "seller": "Edwards（愛德華茲）",
        "name": "【CASIO 】12位元繽紛馬卡龍色系便利型計算機-MS-20UC系列~原廠保固24個月",
        "typeId": 31,
        "type": "文具、美術用具",
        "subType": "學校、辦公用品",
        "item": "計算器",
        "picture": "ID1.jpg",
        "description": "■ MS-20UC\n■ 12位數 \n■ 獨立記憶體\n■ 百分比計算\n■ 利潤率計算\n■ 開根號計算 \n■ 正負數顯示\n■ 倒退鍵\n■ 千分位符號\n■ 時間計算 \n■ 稅金計算\n■ 太陽能和電池雙電力\n■ 長149.5*寬105*高22.8mm\n■ 重量110g",
        "price": 400,
        "amount": 13,
        "fare": 60
    },
    {
        "id": 102,
        "buyer": "Aria",
        "status": "待出貨",
        "seller": "Lewis（劉易斯）",
        "name": "ACER_宏碁XC-1760系列 - i3處理器 - 8G記憶體\n1T + 256G SSD / Win11家用版電腦",
        "typeId": 1,
        "type": "電腦與周邊配件",
        "subType": "桌上型電腦",
        "item": "桌上型電腦",
        "picture": "ID324.jpg,ID324_2.jpg",
        "description": "處理器：Intel Core i3-12100\n主機板晶片組：Intel H610\n記憶體：8GB DDR4 3200MHz = (8G x 1條)(Long-DIMM(U-DIMM) 記憶體支援容量 : 總插槽數量 2 / 最高容量32G)\n硬碟：1TB HDD 7.2K + 256G PCIe M.2 SSD(擴充SATA HDD需購買螺絲*)\n顯示介面：內建\n光碟機：無\n讀卡機：無\n鍵鼠組：有\n音效：Integrated high-definition, 5.1-channel surround sound\n螢幕輸出介面：HDMI\n無線網路：802.11 ax/ac/a/b/g/n, Wi-Fi 6 + Bluetooth® 5.0\n有線網路：RJ45\n電源供應：300W\n作業系統：Windows 11 家用版 (64 bit)\n保固：原廠三年保固/到府收送\n(原廠於保固期內將自行或委託第三方到府收送)  (宏碁家用)\n\n●前端介面\n1x USB 3.2 Gen 1 Type-C™\n1x USB 3.2 Gen 1 Type-A\n1x 3.5mm Headset/speaker jack\n1x Microphone jack\n\n●後端介面\n2x HDMI Port (out)\n4x USB 2.0 Type-A\n1x USB 3.2 Gen1 Type-A\n1x Audio jacks\n1x Ethernet (RJ-45) port\n1x Power connector\n\n體積:100 (W) x 330 (D) x 295 (H) mm",
        "price": 13900,
        "amount": 12,
        "fare": 1500
    },
    {
        "id": 103,
        "buyer": "Aurora",
        "status": "待出貨",
        "seller": "Patel（帕特爾）",
        "name": "ASUS_華碩S500TE系列 - i3處理器 - 8G記憶體\n512G SSD / 無作業系統電腦",
        "typeId": 3,
        "type": "電腦與周邊配件",
        "subType": "桌上型電腦",
        "item": "伺服器主機",
        "picture": "ID72.jpg,ID72_2.jpg",
        "description": "處理器：Intel Core i3-13100\n晶片：Intel B760\n記憶體：記憶體：8GB DDR4 3200MHz = (8G x 1條)(Long-DIMM(U-DIMM)記憶體支援容量 : 總插槽數量 2 / 最高容量64G)\n硬碟：512GB M.2 2280 NVMe™ PCIe® 4.0 SSD(擴充硬碟需自行購買螺絲)\n顯示介面：內顯\n光碟機：無\n讀卡機：無\n鍵鼠組：有\n音效：High Definition 7.1 Channel Audio\n螢幕輸出介面：D-Sub(VGA)．HDMI．DP\n無線網路：Wi-Fi 5(802.11ac) (Dual band) 1*1 + Bluetooth® 5.1 Wireless Card\n有線網路：Intel WGI219V 10/100/1000 Mbps, non-vPro\n電源供應：300W power supply (80+ Bronze, peak 350W)\n作業系統：無作業系統\n保固：原廠三年保固/到府收送\n(免費第一年到府維修)\n(原廠於保固期內將自行或委託第三方到府收送) \n\n●前端 I/O Port\t\n1x Headphone\n1x Mic in\n2x USB 2.0 Type-A\n2x USB 3.2 Gen 1 Type-A\n\n●後端 I/O Port\t\n1x RJ45 Gigabit Ethernet\n1x HDMI 1.4\n1x VGA Port\n1x Display port 1.4\n2x PS2\n3x Audio jacks\n2x USB 2.0 Type-A\n2x USB 3.2 Gen 1 Type-A\n\n●擴充槽(含已使用)\n2x 3.5\"\n4x SATA 6.0Gb/s ports\n2x M.2 connector for storage\n1x PCIe® 4.0 x 16\n2x PCIe® 3.0 x 1\n1x M.2 connector for WiFi\n2x DDR4 U-DIMM slot\n\n體積：17.60 x 39.30 x 38.50 cm (6.93\" x 15.47\" x 15.16\")\n重量：7.70 kg (16.98 lbs)",
        "price": 12618,
        "amount": 8,
        "fare": 1
    },
    {
        "id": 104,
        "buyer": "Ava",
        "status": "待出貨",
        "seller": "Clarke（克拉克）",
        "name": "【Transcend 創見】4TB StoreJet 25M3 軍規防震2.5吋USB3.1行動硬碟-太空灰 (TS4TSJ25M3S)",
        "typeId": 11,
        "type": "電腦與周邊配件",
        "subType": "儲存裝置",
        "item": "內接硬碟/外接硬碟",
        "picture": "ID53.jpg",
        "description": "ID53D.jpg",
        "price": 3399,
        "amount": 15,
        "fare": 1
    },
    {
        "id": 105,
        "buyer": "Aria",
        "status": "完成訂單",
        "seller": "Clarke（克拉克）",
        "name": "【Transcend 創見】2TB StoreJet 25C3S 極致輕薄2.5吋Type C行動硬碟 (TS2TSJ25C3S)",
        "typeId": 11,
        "type": "電腦與周邊配件",
        "subType": "儲存裝置",
        "item": "內接硬碟/外接硬碟",
        "picture": "ID74.jpg",
        "description": "ID74D.jpg",
        "price": 3087,
        "amount": 6,
        "fare": 30
    },
    {
        "id": 106,
        "buyer": "Ann",
        "status": "待出貨",
        "seller": "Hall（霍爾）",
        "name": "DIKE 鳴揚 多功能一體式藍牙喇叭 40W 替代劇院可遙控無線音響(DS606BK)",
        "typeId": 28,
        "type": "影音",
        "subType": "音響/喇叭",
        "item": "音響喇叭",
        "picture": "ID69.jpg",
        "description": "ID69D.jpg",
        "price": 2500,
        "amount": 8,
        "fare": 60
    },
    {
        "id": 107,
        "buyer": "Ada",
        "status": "已收貨",
        "seller": "Edwards（愛德華茲）",
        "name": "【CASIO】12位數工程型計算機2代-(FX-991ESPLUS-2)",
        "typeId": 31,
        "type": "文具、美術用具",
        "subType": "學校、辦公用品",
        "item": "計算器",
        "picture": "ID39.jpg",
        "description": "數學自然顯示\n417個函數\n自然V.P.A.M. 顯示\n如同教科書般的顯示方式\n條列式統計資料編輯器\n多重重現顯示\n10 + 2位數\n新等式模式\n隨機整數\n分數計算\n組合與排列\n統計\n9個變數\n表格函數\n點矩陣顯示\n雙電源系統\n附帶硬式外殼\n尺寸：11.1x77x161.5mm\n重量：95g",
        "price": 850,
        "amount": 5,
        "fare": 60
    },
    {
        "id": 108,
        "buyer": "Anna",
        "status": "完成訂單",
        "seller": "Green（格林）",
        "name": "DIKE 鳴揚 多功能一體式藍牙喇叭 40W 替代劇院可遙控無線音響(DS606BK)",
        "typeId": 28,
        "type": "影音",
        "subType": "音響/喇叭",
        "item": "音響喇叭",
        "picture": "ID69.jpg",
        "description": "ID69D.jpg",
        "price": 2500,
        "amount": 14,
        "fare": 30
    },
    {
        "id": 109,
        "buyer": "Aurora",
        "status": "待出貨",
        "seller": "Patel（帕特爾）",
        "name": "ASUS_華碩S501MD系列 - i5處理器 - 16G記憶體\n1TB SSD / INTEL Arc A380顯卡 / Win11家用版電腦",
        "typeId": 1,
        "type": "電腦與周邊配件",
        "subType": "桌上型電腦",
        "item": "桌上型電腦",
        "picture": "ID81.jpg,ID81_2.jpg",
        "description": "處理器：Intel Core i5-12400F\n主機板晶片組：Intel B660\n記憶體：16GB DDR4 3200MHz = (16G x 1條)(Long-DIMM(U-DIMM) 記憶體支援容量 : 總插槽數量 2 / 最高容量64G)\n硬碟：1TB M.2 2280 NVMe™ PCIe® 3.0 SSD(擴充SATA HDD需購買螺絲*)\n顯示介面：INTEL® Arc™ A380 6GB GDDR6 : 3x DP, 1x HDMI\n光碟機：無\n讀卡機：無\n鍵鼠組：無\n音效：High Definition 7.1 Channel Audio\n螢幕輸出介面：HDMI．DP\n無線網路：Wi-Fi 5(802.11ac) (Dual band) 1*1 + Bluetooth® 5.1 Wireless Card\n有線網路：Intel WGI219V 10/100/1000 Mbps, non-vPro\n電源供應：300W power supply (80+ Bronze, peak 350W)\n作業系統：Windows 11 家用版 (64 bit)\n保固：原廠三年保固/到府收送\n(免費第一年到府維修)\n(原廠於保固期內將自行或委託第三方到府收送)\n\n●前端介面\n1x Headphone\n1x MIC in\n2x USB 2.0 Type-A\n2x USB 3.2 Gen 1 Type-A\n\n●後端介面\n1x RJ45 Gigabit Ethernet\n2x PS2\n3 x Audio jacks\n2x USB 2.0 Type-A\n2x USB 3.2 Gen 1 Type-A\n3x DP (位於顯卡)\n1x HDMI (位於顯卡)\n\n●擴充介面(含已使用)\n1x 3.5\"\n4x SATA 6.0Gb/s ports\n2x M.2 connector for storage\n1x PCIe® 4.0 x 16\n2x PCIe® 3.0 x 1\n1x M.2 connector for WiFi\n2x DDR4 U-DIMM slot\n\n體積:16.00 x 31.89 x 36.78 cm\n重量:5.90 kg",
        "price": 17990,
        "amount": 16,
        "fare": 60
    },
    {
        "id": 110,
        "buyer": "Ada",
        "status": "已出貨",
        "seller": "Brown（布朗）",
        "name": "【Transcend 創見】2TB StoreJet 25C3S 極致輕薄2.5吋Type C行動硬碟 (TS2TSJ25C3S)",
        "typeId": 11,
        "type": "電腦與周邊配件",
        "subType": "儲存裝置",
        "item": "內接硬碟/外接硬碟",
        "picture": "ID74.jpg",
        "description": "ID74D.jpg",
        "price": 2749,
        "amount": 20,
        "fare": 30
    },
    {
        "id": 111,
        "buyer": "Aurora",
        "status": "已收貨",
        "seller": "Clarke（克拉克）",
        "name": "威剛ADATA HD710 PRO 4TB 2.5吋軍規硬碟-黑",
        "typeId": 11,
        "type": "電腦與周邊配件",
        "subType": "儲存裝置",
        "item": "內接硬碟/外接硬碟",
        "picture": "ID83.jpg",
        "description": "ID83D.jpg",
        "price": 3899,
        "amount": 15,
        "fare": 60
    },
    {
        "id": 112,
        "buyer": "Aurora",
        "status": "已收貨",
        "seller": "Jackson（傑克遜）",
        "name": "KINYO 藍牙5.0無線音箱 立體環繞360讀卡喇叭音響，支援藍芽/USB/TF卡/AUX，適用具藍牙功能或3.5mm插孔的平板電腦/筆記型電腦/智慧型手機",
        "typeId": 28,
        "type": "影音",
        "subType": "音響/喇叭",
        "item": "音響喇叭",
        "picture": "ID21.jpg",
        "description": "‧功能控制 藍牙/USB/TF卡/AUX\n‧介面 Bluetooth V5.0\n‧最大接收距離 10M(無任何障礙環境)\n‧輸出功率3W*2 (R.M.S.)\n‧額定電壓 USB DC 5V / 充電電池3.7V\n‧電池規格 聚合物鋰電池1200mAh\n‧消耗電流 200mA\n‧抗阻 4Ω\n‧噪音比 ≧80dB\n‧喇叭單體 2x40mm全音域喇叭\n‧響應頻率 120HZ-20KHz\n‧支援音樂格式MP3\n‧材質 塑料、金屬\n‧產品重量:618g\n‧產品尺寸:400x65x58(WxHxD)mm   \n‧配件 充電線x1、音源線x1",
        "price": 1000,
        "amount": 16,
        "fare": 60
    },
    {
        "id": 113,
        "buyer": "Aurora",
        "status": "已收貨",
        "seller": "Patel（帕特爾）",
        "name": "ASUS_華碩S500TE系列 - i3處理器 - 8G記憶體\n512G SSD / Win11家用版電腦",
        "typeId": 1,
        "type": "電腦與周邊配件",
        "subType": "桌上型電腦",
        "item": "桌上型電腦",
        "picture": "ID85.jpg,ID85_2.jpg",
        "description": "處理器：Intel Core i3-13100\n晶片：Intel B760\n記憶體：記憶體：8GB DDR4 3200MHz = (8G x 1條)(Long-DIMM(U-DIMM)記憶體支援容量 : 總插槽數量 2 / 最高容量64G)\n硬碟：512GB M.2 2280 NVMe™ PCIe® 4.0 SSD(擴充硬碟需自行購買螺絲)\n顯示介面：內顯\n光碟機：無\n讀卡機：無\n鍵鼠組：有\n音效：High Definition 7.1 Channel Audio\n螢幕輸出介面：D-Sub(VGA)．HDMI．DP\n無線網路：Wi-Fi 5(802.11ac) (Dual band) 1*1 + Bluetooth® 5.1 Wireless Card\n有線網路：Intel WGI219V 10/100/1000 Mbps, non-vPro\n電源供應：300W power supply (80+ Bronze, peak 350W)\n作業系統：Windows 11 家用版 (64 bit)\n保固：原廠三年保固/到府收送\n(免費第一年到府維修)\n(原廠於保固期內將自行或委託第三方到府收送) \n\n●前端 I/O Port\t\n1x Headphone\n1x Mic in\n2x USB 2.0 Type-A\n2x USB 3.2 Gen 1 Type-A\n\n●後端 I/O Port\t\n1x RJ45 Gigabit Ethernet\n1x HDMI 1.4\n1x VGA Port\n1x Display port 1.4\n2x PS2\n3x Audio jacks\n2x USB 2.0 Type-A\n2x USB 3.2 Gen 1 Type-A\n\n●擴充槽(含已使用)\n2x 3.5\"\n4x SATA 6.0Gb/s ports\n2x M.2 connector for storage\n1x PCIe® 4.0 x 16\n2x PCIe® 3.0 x 1\n1x M.2 connector for WiFi\n2x DDR4 U-DIMM slot\n\n體積：17.60 x 39.30 x 38.50 cm (6.93\" x 15.47\" x 15.16\")\n重量：7.70 kg (16.98 lbs)",
        "price": 14618,
        "amount": 6,
        "fare": 1500
    },
    {
        "id": 114,
        "buyer": "Ariana",
        "status": "完成訂單",
        "seller": "Edwards（愛德華茲）",
        "name": "卡西歐CASIO桌上型計算機/12位元/MX-12B",
        "typeId": 31,
        "type": "文具、美術用具",
        "subType": "學校、辦公用品",
        "item": "計算器",
        "picture": "ID86.jpg",
        "description": "ID86D.jpg",
        "price": 320,
        "amount": 10,
        "fare": 1
    },
    {
        "id": 115,
        "buyer": "Ann",
        "status": "已出貨",
        "seller": "Evans（埃文斯）",
        "name": "【CASIO】12位數工程型計算機2代-(FX-991ESPLUS-2)",
        "typeId": 31,
        "type": "文具、美術用具",
        "subType": "學校、辦公用品",
        "item": "計算器",
        "picture": "ID39.jpg",
        "description": "數學自然顯示\n417個函數\n自然V.P.A.M. 顯示\n如同教科書般的顯示方式\n條列式統計資料編輯器\n多重重現顯示\n10 + 2位數\n新等式模式\n隨機整數\n分數計算\n組合與排列\n統計\n9個變數\n表格函數\n點矩陣顯示\n雙電源系統\n附帶硬式外殼\n尺寸：11.1x77x161.5mm\n重量：95g",
        "price": 870,
        "amount": 5,
        "fare": 60
    },
    {
        "id": 116,
        "buyer": "Anna",
        "status": "已出貨",
        "seller": "Brown（布朗）",
        "name": "威剛ADATA HD710 PRO 4TB 2.5吋軍規硬碟-黑",
        "typeId": 11,
        "type": "電腦與周邊配件",
        "subType": "儲存裝置",
        "item": "內接硬碟/外接硬碟",
        "picture": "ID83.jpg",
        "description": "ID83D.jpg",
        "price": 3899,
        "amount": 20,
        "fare": 60
    },
    {
        "id": 117,
        "buyer": "Ada",
        "status": "已收貨",
        "seller": "Hall（霍爾）",
        "name": "小愛同學｜聲控家電｜您的智能管家",
        "typeId": 28,
        "type": "影音",
        "subType": "音響/喇叭",
        "item": "音響喇叭",
        "picture": "ID93.jpg",
        "description": "ID93D.jpg",
        "price": 890,
        "amount": 8,
        "fare": 30
    },
    {
        "id": 118,
        "buyer": "Abigail",
        "status": "待出貨",
        "seller": "Green（格林）",
        "name": "小愛同學｜聲控家電｜您的智能管家",
        "typeId": 28,
        "type": "影音",
        "subType": "音響/喇叭",
        "item": "音響喇叭",
        "picture": "ID93.jpg",
        "description": "ID93D.jpg",
        "price": 900,
        "amount": 13,
        "fare": 30
    },
    {
        "id": 119,
        "buyer": "Amelia",
        "status": "已出貨",
        "seller": "Jackson（傑克遜）",
        "name": "DIKE 鳴揚 多功能一體式藍牙喇叭 40W 替代劇院可遙控無線音響(DS606BK)",
        "typeId": 28,
        "type": "影音",
        "subType": "音響/喇叭",
        "item": "音響喇叭",
        "picture": "ID69.jpg",
        "description": "ID69D.jpg",
        "price": 2450,
        "amount": 5,
        "fare": 60
    }
]